Workbook
Name Age_Groups: Customer_Helper!$P$1:$S$6
Name City_Assignment: Salesperson_Helper!$H$1:$I$11
Name City_Master: Customer_Helper!$F$1:$H$13
Name Customer_Segments: Orders_Helper!$J$1:$L$4
Name Customer_Types: Customer_Helper!$J$1:$K$4
Name Electronics_Products: #REF!
Name First_Names: Customer_Helper!$A$1:$B$101
Name Furniture_Products: #REF!
Name Gender_Distribution: Customer_Helper!$M$1:$N$3
Name Last_Names: Customer_Helper!$D$1:$D$51
Name Monthly_Distribution: Orders_Helper!$F$1:$H$12
Name Order_Distribution: Orders_Helper!$A$1:$D$4
Name Product_MasterData: Product_Masterdata!$A$1:$L$22
Name Raw_Data: Raw_data!#REF!
Name Region: Salesperson_Helper!$K$1:$L$13
Name Salesperson_Master: Salesperson_Masterdata!$A$1:$F$11
Name Salesperson_Names: Salesperson_Helper!$A$1:$C$11
Name Seasonal_Mapping: Master_data!$A$15:$B$27
Name tbl_cities: Master_data!$A$1:$B$13
Name tbl_paymentmode: Master_data!$N$1:$N$6
Name tbl_products: Master_data!$E$1:$G$31
Name tbl_saleschannel: Master_data!$P$1:$P$3
Name tbl_salesperson: Master_data!$J$1:$K$11
Name Team_Assignment: Salesperson_Helper!$E$1:$F$11
Name Weekly_Behaviour: Orders_Helper!$N$1:$O$8

Sheet Dashboard
A1: NOVAMART RETAIL SALES AND PROFIT ANALYSIS | AA1: Rank | AB1: Product | AC1: Revenue | AD1: Revenue Lable
AA2: =ROW(Y1) -> 1 | AB2: =INDEX(Product_Analysis[Product],MATCH(AC2,Product_Analysis[Revenue],0)) -> Laptop | AC2: =LARGE(Product_Analysis[Revenue],AA2) -> 24771000 | AD2: ="₹"&TEXT(Product_helper_Dashboard[[#This Row],[Revenue]]/10000000,"0.00")&" Cr" -> ₹2.48 Cr | AF2: =SUM(RawData[Revenue]) -> 1.2407907e+08
A3: FY 2025 | Sales Performance Dashboard | AA3: =ROW(Y2) -> 2 | AB3: =INDEX(Product_Analysis[Product],MATCH(AC3,Product_Analysis[Revenue],0)) -> Sofa | AC3: =LARGE(Product_Analysis[Revenue],AA3) -> 16882267 | AD3: ="₹"&TEXT(Product_helper_Dashboard[[#This Row],[Revenue]]/10000000,"0.00")&" Cr" -> ₹1.69 Cr | AF3: =SUM(RawData[Profit]) -> 17118773
AA4: =ROW(Y3) -> 3 | AB4: =INDEX(Product_Analysis[Product],MATCH(AC4,Product_Analysis[Revenue],0)) -> Smartphone | AC4: =LARGE(Product_Analysis[Revenue],AA4) -> 16236016 | AD4: ="₹"&TEXT(Product_helper_Dashboard[[#This Row],[Revenue]]/10000000,"0.00")&" Cr" -> ₹1.62 Cr | AF4: =ROWS(RawData[Order_ID]) -> 3000
A5: Total Revenue | C5: Total Profit | E5: Profit Margin | G5: Total Orders | I5: Units Sold | K5: Customers | M5: Avg. Order Value | AA5: =ROW(Y4) -> 4 | AB5: =INDEX(Product_Analysis[Product],MATCH(AC5,Product_Analysis[Revenue],0)) -> Wardrobe | AC5: =LARGE(Product_Analysis[Revenue],AA5) -> 12427452 | AD5: ="₹"&TEXT(Product_helper_Dashboard[[#This Row],[Revenue]]/10000000,"0.00")&" Cr" -> ₹1.24 Cr
A6: ="₹"&TEXT(AF2/10000000,"0.00")&" Cr" -> ₹12.41 Cr | C6: ="₹"&TEXT(AF3/10000000,"0.00")&" Cr" -> ₹1.71 Cr | E6: =SUM(RawData[Profit])/SUM(RawData[Revenue]) -> 0.13796665 | G6: =ROWS(RawData[Order_ID]) -> 3000 | I6: =SUM(RawData[Quantity]) -> 9029 | K6: =COUNTA(Customer_Masterdata[Customer_ID]) -> 900 | M6: ="₹"&TEXT(AF6/1000,"0.00")&" K" -> ₹41.36 K | AA6: =ROW(Y5) -> 5 | AB6: =INDEX(Product_Analysis[Product],MATCH(AC6,Product_Analysis[Revenue],0)) -> Tablet | AC6: =LARGE(Product_Analysis[Revenue],AA6) -> 11092822 | AD6: ="₹"&TEXT(Product_helper_Dashboard[[#This Row],[Revenue]]/10000000,"0.00")&" Cr" -> ₹1.11 Cr | AF6: =AF2/AF4 -> 41359.689
A71: Key Business Insights
A72: Insight 1 | C72: Insight 2 | F72: Insight 3 | I72: Insight 4 | L72: Insight 5
A73: West is NovaMart's strongest region | C73: Electronics drives revenue, while Office Supplies drives margin | F73: Occasional and Loyal customers drive the business | I73: November–December show a major profitability decline | L73: High-revenue products require margin protection
A77: ⚠️ Profitability Alert: November and December margins declined sharply to 6.99% and 6.10%, compared with ~14.7–15.4% in most other months. The decline is concentrated in Electronics and Furniture and coincides with high seasonal discounts
A80: Margin Insight: Electronics and Furniture experienced substantial margin compression during the festival period, while Office Supplies remained consistently above 27% margin.

Sheet Analysis
A1: Metric | B1: My Excel Result | D1: Category Analysis | L1: Monthly Analysis | T1: Category and Seasonal Analysis | AD1: Product Analysis | AL1: Customer Analysis | AU1: Customer Segment Summary | BG1: Top 10 Customers by revenue | BN1: Top 10 Customers by Profit | BU1: Sales Channel Analysis | CC1: Payment Mode Analysis | CK1: Salesperson Analysis | CU1: City Performance | DC1: Region Performance | DK1: Profit_Drop_Analysis | DQ1: Product_Level_Investigation | DY1: Monthly Analysis | EG1: Product_Discount_Analysis
A2: Total Transactions | B2: =COUNTA(RawData[Order_ID]) -> 3000 | D2: Category | E2: Orders | F2: Units Sold | G2: Revenue | H2: Cost | I2: Profit | J2: Profit Margin | L2: Month | M2: Month Number | N2: Orders | O2: Units Sold | P2: Revenue | Q2: Profit | R2: Profit Margin | T2: Category | U2: Season | V2: Orders | W2: Units Sold | X2: Revenue | Y2: Profit | Z2: Profit Margin | AA2: Revenue Lable | AB2: Profit Lable | AD2: Product | AE2: Category | AF2: Orders | AG2: Units Sold | AH2: Revenue | AI2: Profit | AJ2: Profit Margin | AL2: Customer ID | AM2: Customer Name | AN2: Orders | AO2: Units Sold | AP2: Revenue | AQ2: Profit | AR2: AOV | AS2: Customer Type | AU2: Customer Type | AV2: Customers | AW2: Orders | AX2: Units | AY2: Revenue | AZ2: Profit | BA2: Profit Margin | BB2: Avg Revenue per Customer | BC2: Avg Profit per Customer | BD2: Avg Orders per Customer | BE2: Revenue Lable | BG2: Rank | BH2: Customer ID | BI2: Customer Name | BJ2: Orders | BK2: Revenue | BL2: Profit | BN2: Rank | BO2: Customer ID | BP2: Customer Name | BQ2: Orders | BR2: Revenue | BS2: Profit | BU2: Sales Channel | BV2: Orders | BW2: Units Sold | BX2: Revenue | BY2: Profit | BZ2: Profit Margin | CA2: Revenue Lable | CC2: Payment Mode | CD2: Orders | CE2: Units Sold | CF2: Revenue | CG2: Profit | CH2: Profit Margin | CI2: Revenue Lable | CK2: Salesperson ID | CL2: Salesperson Name | CM2: Orders | CN2: Units Sold | CO2: Revenue | CP2: Profit | CQ2: Profit Margin | CR2: Avg Order Value | CS2: Revenue Lable | CU2: City | CV2: Region | CW2: Orders | CX2: Units Sold | CY2: Revenue | CZ2: Profit | DA2: Profit Margin | DC2: Region | DD2: Orders | DE2: Units Sold | DF2: Revenue | DG2: Profit | DH2: Profit Margin | DI2: Revenue Lable | DK2: Month | DL2: Category | DM2: Revenue | DN2: Profit | DO2: Margin | DQ2: Product | DR2: Nov Revenue | DS2: Nov Profit | DT2: Nov Margin | DU2: Dec Revenue | DV2: Dec Profit | DW2: Dec Margin | DY2: Month | DZ2: Month Number | EA2: Orders | EB2: Units Sold | EC2: Revenue | ED2: Profit | EE2: Profit Margin | EG2: Product | EH2: Normal Margin | EI2: Nov Margin | EJ2: Nov Discount | EK2: Dec Margin | EL2: Dec Discount
A3: Unique products | B3: =SUMPRODUCT((RawData[Product_ID]<>"")/COUNTIF(RawData[Product_ID],RawData[Product_ID]&"")) -> 21 | D3: Electronics | E3: =COUNTIF(RawData[Product_Category],"Electronics") -> 1472 | F3: =SUMIF(RawData[Product_Category],"Electronics",RawData[Quantity]) -> 4460 | G3: =SUMIF(RawData[Product_Category],"Electronics",RawData[Revenue]) -> 73862420 | H3: =SUMIF(RawData[Product_Category],"Electronics",RawData[Total_Cost]) -> 64679145 | I3: =SUMIF(RawData[Product_Category],"Electronics",RawData[Profit]) -> 9183274.6 | J3: =I3/G3 -> 0.12432946 | L3: January | M3: =MONTH(L3&1) -> 1 | N3: =SUMPRODUCT(--(MONTH(RawData[Order_Date])= M3)) -> 292 | O3: =SUMPRODUCT((MONTH(RawData[Order_Date])=M3)*RawData[Quantity]) -> 860 | P3: =SUMPRODUCT((MONTH(RawData[Order_Date])=M3)*RawData[Revenue]) -> 11736181 | Q3: =SUMPRODUCT((MONTH(RawData[Order_Date])=M3)*RawData[Profit]) -> 1796861.2 | R3: =IFERROR(Q3/P3,0) -> 0.15310442 | T3: Electronics | U3: Regular | V3: =COUNTIFS(RawData[Product_Category],"Electronics",RawData[Order_Date],"<"&DATE(2025,11,1)) -> 1229 | W3: =SUMIFS(RawData[Quantity],RawData[Product_Category],"Electronics",RawData[Order_Date],"<"&DATE(2025,11,1)) -> 3710 | X3: =SUMIFS(RawData[Revenue],RawData[Product_Category],"Electronics",RawData[Order_Date],"<"&DATE(2025,11,1)) -> 62713704 | Y3: =SUMIFS(RawData[Profit],RawData[Product_Category],"Electronics",RawData[Order_Date],"<"&DATE(2025,11,1)) -> 8574838.7 | Z3: =Y3/X3 -> 0.13672991 | AA3: ="₹"&TEXT(Category_and_Seasonal_Analysis[[#This Row],[Revenue]]/10000000,"0.00")&" Cr" -> ₹6.27 Cr | AB3: ="₹"&TEXT(Category_and_Seasonal_Analysis[[#This Row],[Profit]]/100000,"0.00")&" L" -> ₹85.75 L | AD3: Laptop | AE3: Electronics | AF3: =COUNTIF(RawData[Product_Name],AD3) -> 150 | AG3: =SUMIF(RawData[Product_Name],AD3,RawData[Quantity]) -> 483 | AH3: =SUMIF(RawData[Product_Name],AD3,RawData[Revenue]) -> 24771000 | AI3: =SUMIF(RawData[Product_Name],AD3,RawData[Profit]) -> 2988095.7 | AJ3: =AI3/AH3 -> 0.12062879 | AL3: C0001 | AM3: Prachi Choudhary | AN3: =COUNTIF(RawData[Customer_ID],AL3) -> 2 | AO3: =SUMIF(RawData[Customer_ID],AL3,RawData[Quantity]) -> 9 | AP3: =SUMIF(RawData[Customer_ID],AL3,RawData[Revenue]) -> 37162.5 | AQ3: =SUMIF(RawData[Customer_ID],AL3,RawData[Profit]) -> 9787.5 | AR3: =IF(AN3=0,0,AP3/AN3) -> 18581.25 | AS3: =IF(AN3=1,"One-time",IF(AN3<=4,"Occasional",IF(AN3<=8,"Loyal","Review"))) -> Occasional | AU3: One-time | AV3: =COUNTIF(Customer_Analysis[Customer Type],AU3) -> 101 | AW3: =SUMIF(Customer_Analysis[Customer Type],AU3,Customer_Analysis[Orders]) -> 101 | AX3: =SUMIF(Customer_Analysis[Customer Type],AU3,Customer_Analysis[Units Sold]) -> 321 | AY3: =SUMIF(Customer_Analysis[Customer Type],AU3,Customer_Analysis[Revenue]) -> 3849440.8 | AZ3: =SUMIF(Customer_Analysis[Customer Type],AU3,Customer_Analysis[Profit]) -> 509725.48 | BA3: =AZ3/AY3 -> 0.13241546 | BB3: =AY3/AV3 -> 38113.275 | BC3: =AZ3/AV3 -> 5046.7869 | BD3: =AW3/AV3 -> 1 | BE3: ="₹"&TEXT(Customer_Segment_Analysis[[#This Row],[Revenue]]/10000000,"0.00")&" Cr" -> ₹0.38 Cr | BG3: 1 | BH3: C0012 | BI3: Trisha Jain | BJ3: 4 | BK3: 688035.24 | BL3: 83323.21 | BN3: 1 | BO3: C0846 | BP3: Nikita Saxena | BQ3: 7 | BR3: 586628.8 | BS3: 89714.14 | BU3: Online | BV3: =COUNTIF(RawData[Sales_Channel],BU3) -> 1139 | BW3: =SUMIF(RawData[Sales_Channel],BU3,RawData[Quantity]) -> 3351 | BX3: =SUMIF(RawData[Sales_Channel],BU3,RawData[Revenue]) -> 46169839 | BY3: =SUMIF(RawData[Sales_Channel],BU3,RawData[Profit]) -> 6425730.1 | BZ3: =BY3/BX3 -> 0.13917593 | CA3: ="₹"&TEXT(Sales_Channel_Analysis[[#This Row],[Revenue]]/10000000,"0.00")&" Cr" -> ₹4.62 Cr | CC3: UPI | CD3: =COUNTIF(RawData[Payment_Mode],CC3) -> 1160 | CE3: =SUMIF(RawData[Payment_Mode],CC3,RawData[Quantity]) -> 3548 | CF3: =SUMIF(RawData[Payment_Mode],CC3,RawData[Revenue]) -> 48443973 | CG3: =SUMIF(RawData[Payment_Mode],CC3,RawData[Profit]) -> 6615684.4 | CH3: =CG3/CF3 -> 0.13656362 | CI3: ="₹"&TEXT(Payment_Mode_Analysis[[#This Row],[Revenue]]/10000000,"0.00")&" Cr" -> ₹4.84 Cr | CK3: S001 | CL3: Aarav Patel | CM3: =COUNTIF(RawData[Salesperson_ID],CK3) -> 308 | CN3: =SUMIF(RawData[Salesperson_ID],CK3,RawData[Quantity]) -> 861 | CO3: =SUMIF(RawData[Salesperson_ID],CK3,RawData[Revenue]) -> 11723932 | CP3: =SUMIF(RawData[Salesperson_ID],CK3,RawData[Profit]) -> 1603525.7 | CQ3: =CP3/CO3 -> 0.13677372 | CR3: =IF(CM3=0,0,CO3/CM3) -> 38064.713 | CS3: ="₹"&TEXT(Table29[[#This Row],[Revenue]]/10000000,"0.00")&" Cr" -> ₹1.17 Cr | CU3: Mumbai | CV3: West | CW3: =COUNTIF(RawData[City],CU3) -> 238 | CX3: =SUMIF(RawData[City],CU3,RawData[Quantity]) -> 694 | CY3: =SUMIF(RawData[City],CU3,RawData[Revenue]) -> 9835614 | CZ3: =SUMIF(RawData[City],CU3,RawData[Profit]) -> 1335614 | DA3: =CZ3/CY3 -> 0.13579366 | DC3: North | DD3: =SUMIF(City_Analysis[Region],DC3,City_Analysis[Orders]) -> 749 | DE3: =SUMIF(City_Analysis[Region],DC3,City_Analysis[Units Sold]) -> 2271 | DF3: =SUMIF(City_Analysis[Region],DC3,City_Analysis[Revenue]) -> 31221257 | DG3: =SUMIF(City_Analysis[Region],DC3,City_Analysis[Profit]) -> 4345091 | DH3: =IF(DF3=0,0,DG3/DF3) -> 0.13917092 | DI3: ="₹"&TEXT(Region_Analysis[[#This Row],[Revenue]]/10000000,"0.00")&" Cr" -> ₹3.12 Cr | DK3: November | DL3: Electronics | DM3: =SUMIFS(RawData[Revenue],RawData[Product_Category],DL3, RawData[Order_Date],">="&DATE(2025,11,1),RawData[Order_Date],"<"&DATE(2025,12,1)) -> 5182808.7 | DN3: =SUMIFS(RawData[Profit],RawData[Product_Category],Profit_Drop_Analysis[[#This Row],[Category]], RawData[Order_Date],">="&DATE(2025,11,1),RawData[Order_Date],"<"&DATE(2025,12,1)) -> 327958.16 | DO3: =DN3/DM3 -> 0.063278076 | DQ3: Laptop | DR3: =SUMIFS(RawData[Revenue],RawData[Product_Name],DQ3, RawData[Order_Date],">="&DATE(2025,11,1),RawData[Order_Date],"<"&DATE(2025,12,1)) -> 946532.79 | DS3: =SUMIFS(RawData[Profit],RawData[Product_Name],DQ3, RawData[Order_Date],">="&DATE(2025,11,1),RawData[Order_Date],"<"&DATE(2025,12,1)) -> 44549.19 | DT3: =DS3/DR3 -> 0.04706566 | DU3: =SUMIFS(RawData[Revenue],RawData[Product_Name],DQ3, RawData[Order_Date],">="&DATE(2025,12,1),RawData[Order_Date],"<"&DATE(2026,1,1)) -> 1256177.2 | DV3: =SUMIFS(RawData[Profit],RawData[Product_Name],DQ3, RawData[Order_Date],">="&DATE(2025,12,1),RawData[Order_Date],"<"&DATE(2026,1,1)) -> 38499.3 | DW3: =DV3/DU3 -> 0.030647986 | DY3: January | DZ3: =MONTH(DY3&1) -> 1 | EA3: =SUMPRODUCT(--(MONTH(RawData[Order_Date])= DZ3)) -> 292 | EB3: =SUMPRODUCT((MONTH(RawData[Order_Date])=DZ3)*RawData[Quantity]) -> 860 | EC3: =SUMPRODUCT((MONTH(RawData[Order_Date])=DZ3)*RawData[Revenue]) -> 11736181 | ED3: =SUMPRODUCT((MONTH(RawData[Order_Date])=DZ3)*RawData[Profit]) -> 1796861.2 | EE3: =IFERROR(ED3/EC3,0) -> 0.15310442 | EG3: Laptop | EH3: =VLOOKUP(EG3,Product_Analysis[[Product]:[Profit Margin]],7,FALSE) -> 0.12062879 | EI3: 0.0471 | EJ3: =AVERAGEIFS(RawData[Discount%],RawData[Product_Name],EG3,RawData[Order_Date],">="&DATE(2025,11,1),RawData[Order_Date],"<"&DATE(2025,12,1)) -> 14.333333 | EK3: 0.030647986 | EL3: =AVERAGEIFS(RawData[Discount%],RawData[Product_Name],EG3,RawData[Order_Date],">="&DATE(2025,12,1),RawData[Order_Date],"<"&DATE(2026,1,1)) -> 15
A4: Unique Customers | B4: =SUMPRODUCT((RawData[Customer_ID]<>"")/COUNTIF(RawData[Customer_ID],RawData[Customer_ID]&"")) -> 864 | D4: Furniture | E4: =COUNTIF(RawData[Product_Category],"Furniture") -> 816 | F4: =SUMIF(RawData[Product_Category],"Furniture",RawData[Quantity]) -> 2423 | G4: =SUMIF(RawData[Product_Category],"Furniture",RawData[Revenue]) -> 49718569 | H4: =SUMIF(RawData[Product_Category],"Furniture",RawData[Total_Cost]) -> 41920658 | I4: =SUMIF(RawData[Product_Category],"Furniture",RawData[Profit]) -> 7797911 | J4: =I4/G4 -> 0.15684102 | L4: February | M4: =MONTH(L4&1) -> 2 | N4: =SUMPRODUCT(--(MONTH(RawData[Order_Date])= M4)) -> 222 | O4: =SUMPRODUCT((MONTH(RawData[Order_Date])=M4)*RawData[Quantity]) -> 658 | P4: =SUMPRODUCT((MONTH(RawData[Order_Date])=M4)*RawData[Revenue]) -> 9441583.4 | Q4: =SUMPRODUCT((MONTH(RawData[Order_Date])=M4)*RawData[Profit]) -> 1413047.1 | R4: =IFERROR(Q4/P4,0) -> 0.14966209 | T4: Electronics | U4: Festival | V4: =COUNTIFS(RawData[Product_Category],"Electronics",RawData[Order_Date],">="&DATE(2025,11,1)) -> 243 | W4: =SUMIFS(RawData[Quantity],RawData[Product_Category],"Electronics",RawData[Order_Date],">="&DATE(2025,11,1)) -> 750 | X4: =SUMIFS(RawData[Revenue],RawData[Product_Category],"Electronics",RawData[Order_Date],">="&DATE(2025,11,1)) -> 11148716 | Y4: =SUMIFS(RawData[Profit],RawData[Product_Category],"Electronics",RawData[Order_Date],">="&DATE(2025,11,1)) -> 608435.89 | Z4: =Y4/X4 -> 0.054574525 | AA4: ="₹"&TEXT(Category_and_Seasonal_Analysis[[#This Row],[Revenue]]/10000000,"0.00")&" Cr" -> ₹1.11 Cr | AB4: ="₹"&TEXT(Category_and_Seasonal_Analysis[[#This Row],[Profit]]/100000,"0.00")&" L" -> ₹6.08 L | AD4: Smartphone | AE4: Electronics | AF4: =COUNTIF(RawData[Product_Name],AD4) -> 165 | AG4: =SUMIF(RawData[Product_Name],AD4,RawData[Quantity]) -> 492 | AH4: =SUMIF(RawData[Product_Name],AD4,RawData[Revenue]) -> 16236016 | AI4: =SUMIF(RawData[Product_Name],AD4,RawData[Profit]) -> 2145136 | AJ4: =AI4/AH4 -> 0.13212207 | AL4: C0002 | AM4: Palak Pawar | AN4: =COUNTIF(RawData[Customer_ID],AL4) -> 2 | AO4: =SUMIF(RawData[Customer_ID],AL4,RawData[Quantity]) -> 5 | AP4: =SUMIF(RawData[Customer_ID],AL4,RawData[Revenue]) -> 4929 | AQ4: =SUMIF(RawData[Customer_ID],AL4,RawData[Profit]) -> 1545 | AR4: =IF(AN4=0,0,AP4/AN4) -> 2464.5 | AS4: =IF(AN4=1,"One-time",IF(AN4<=4,"Occasional",IF(AN4<=8,"Loyal","Review"))) -> Occasional | AU4: Occasional | AV4: =COUNTIF(Customer_Analysis[Customer Type],AU4) -> 568 | AW4: =SUMIF(Customer_Analysis[Customer Type],AU4,Customer_Analysis[Orders]) -> 1551 | AX4: =SUMIF(Customer_Analysis[Customer Type],AU4,Customer_Analysis[Units Sold]) -> 4622 | AY4: =SUMIF(Customer_Analysis[Customer Type],AU4,Customer_Analysis[Revenue]) -> 64466271 | AZ4: =SUMIF(Customer_Analysis[Customer Type],AU4,Customer_Analysis[Profit]) -> 8910939.8 | BA4: =AZ4/AY4 -> 0.13822639 | BB4: =AY4/AV4 -> 113496.96 | BC4: =AZ4/AV4 -> 15688.274 | BD4: =AW4/AV4 -> 2.7306338 | BE4: ="₹"&TEXT(Customer_Segment_Analysis[[#This Row],[Revenue]]/10000000,"0.00")&" Cr" -> ₹6.45 Cr | BG4: 2 | BH4: C0416 | BI4: Krish Kapoor | BJ4: 8 | BK4: 638645.89 | BL4: 65781.6 | BN4: 2 | BO4: C0296 | BP4: Kunal Kaur | BQ4: 7 | BR4: 513962.99 | BS4: 88176.92 | BU4: Corporate | BV4: =COUNTIF(RawData[Sales_Channel],BU4) -> 201 | BW4: =SUMIF(RawData[Sales_Channel],BU4,RawData[Quantity]) -> 595 | BX4: =SUMIF(RawData[Sales_Channel],BU4,RawData[Revenue]) -> 7696048.1 | BY4: =SUMIF(RawData[Sales_Channel],BU4,RawData[Profit]) -> 1110137.6 | BZ4: =BY4/BX4 -> 0.14424775 | CA4: ="₹"&TEXT(Sales_Channel_Analysis[[#This Row],[Revenue]]/10000000,"0.00")&" Cr" -> ₹0.77 Cr | CC4: Credit Card | CD4: =COUNTIF(RawData[Payment_Mode],CC4) -> 743 | CE4: =SUMIF(RawData[Payment_Mode],CC4,RawData[Quantity]) -> 2207 | CF4: =SUMIF(RawData[Payment_Mode],CC4,RawData[Revenue]) -> 30885641 | CG4: =SUMIF(RawData[Payment_Mode],CC4,RawData[Profit]) -> 4374285 | CH4: =CG4/CF4 -> 0.14162843 | CI4: ="₹"&TEXT(Payment_Mode_Analysis[[#This Row],[Revenue]]/10000000,"0.00")&" Cr" -> ₹3.09 Cr | CK4: S002 | CL4: Priya Shah | CM4: =COUNTIF(RawData[Salesperson_ID],CK4) -> 287 | CN4: =SUMIF(RawData[Salesperson_ID],CK4,RawData[Quantity]) -> 854 | CO4: =SUMIF(RawData[Salesperson_ID],CK4,RawData[Revenue]) -> 11599043 | CP4: =SUMIF(RawData[Salesperson_ID],CK4,RawData[Profit]) -> 1558798 | CQ4: =CP4/CO4 -> 0.13439023 | CR4: =IF(CM4=0,0,CO4/CM4) -> 40414.783 | CS4: ="₹"&TEXT(Table29[[#This Row],[Revenue]]/10000000,"0.00")&" Cr" -> ₹1.16 Cr | CU4: Pune | CV4: West | CW4: =COUNTIF(RawData[City],CU4) -> 219 | CX4: =SUMIF(RawData[City],CU4,RawData[Quantity]) -> 653 | CY4: =SUMIF(RawData[City],CU4,RawData[Revenue]) -> 7436394.5 | CZ4: =SUMIF(RawData[City],CU4,RawData[Profit]) -> 1043534.7 | DA4: =CZ4/CY4 -> 0.14032804 | DC4: South | DD4: =SUMIF(City_Analysis[Region],DC4,City_Analysis[Orders]) -> 783 | DE4: =SUMIF(City_Analysis[Region],DC4,City_Analysis[Units Sold]) -> 2385 | DF4: =SUMIF(City_Analysis[Region],DC4,City_Analysis[Revenue]) -> 31841025 | DG4: =SUMIF(City_Analysis[Region],DC4,City_Analysis[Profit]) -> 4381866.9 | DH4: =IF(DF4=0,0,DG4/DF4) -> 0.13761702 | DI4: ="₹"&TEXT(Region_Analysis[[#This Row],[Revenue]]/10000000,"0.00")&" Cr" -> ₹3.18 Cr | DK4: November | DL4: Furniture | DM4: =SUMIFS(RawData[Revenue],RawData[Product_Category],DL4, RawData[Order_Date],">="&DATE(2025,11,1),RawData[Order_Date],"<"&DATE(2025,12,1)) -> 3684981.1 | DN4: =SUMIFS(RawData[Profit],RawData[Product_Category],Profit_Drop_Analysis[[#This Row],[Category]], RawData[Order_Date],">="&DATE(2025,11,1),RawData[Order_Date],"<"&DATE(2025,12,1)) -> 284057.81 | DO4: =DN4/DM4 -> 0.077085282 | DQ4: Smartphone | DR4: =SUMIFS(RawData[Revenue],RawData[Product_Name],DQ4, RawData[Order_Date],">="&DATE(2025,11,1),RawData[Order_Date],"<"&DATE(2025,12,1)) -> 2016614 | DS4: =SUMIFS(RawData[Profit],RawData[Product_Name],DQ4, RawData[Order_Date],">="&DATE(2025,11,1),RawData[Order_Date],"<"&DATE(2025,12,1)) -> 155014 | DT4: =DS4/DR4 -> 0.076868454 | DU4: =SUMIFS(RawData[Revenue],RawData[Product_Name],DQ4, RawData[Order_Date],">="&DATE(2025,12,1),RawData[Order_Date],"<"&DATE(2026,1,1)) -> 1479972 | DV4: =SUMIFS(RawData[Profit],RawData[Product_Name],DQ4, RawData[Order_Date],">="&DATE(2025,12,1),RawData[Order_Date],"<"&DATE(2026,1,1)) -> 105252 | DW4: =DV4/DU4 -> 0.071117562 | DY4: February | DZ4: =MONTH(DY4&1) -> 2 | EA4: =SUMPRODUCT(--(MONTH(RawData[Order_Date])= DZ4)) -> 222 | EB4: =SUMPRODUCT((MONTH(RawData[Order_Date])=DZ4)*RawData[Quantity]) -> 658 | EC4: =SUMPRODUCT((MONTH(RawData[Order_Date])=DZ4)*RawData[Revenue]) -> 9441583.4 | ED4: =SUMPRODUCT((MONTH(RawData[Order_Date])=DZ4)*RawData[Profit]) -> 1413047.1 | EE4: =IFERROR(ED4/EC4,0) -> 0.14966209 | EG4: Smartphone | EH4: =VLOOKUP(EG4,Product_Analysis[[Product]:[Profit Margin]],7,FALSE) -> 0.13212207 | EI4: 0.076868454 | EJ4: =AVERAGEIFS(RawData[Discount%],RawData[Product_Name],EG4,RawData[Order_Date],">="&DATE(2025,11,1),RawData[Order_Date],"<"&DATE(2025,12,1)) -> 13.7 | EK4: 0.071117562 | EL4: =AVERAGEIFS(RawData[Discount%],RawData[Product_Name],EG4,RawData[Order_Date],">="&DATE(2025,12,1),RawData[Order_Date],"<"&DATE(2026,1,1)) -> 14.142857
A5: Unique Salespersons | B5: =SUMPRODUCT((RawData[Salesperson_ID]<>"")/COUNTIF(RawData[Salesperson_ID],RawData[Salesperson_ID]&"")) -> 10 | D5: Office Supplies | E5: =COUNTIF(RawData[Product_Category],"Office Supplies") -> 712 | F5: =SUMIF(RawData[Product_Category],"Office Supplies",RawData[Quantity]) -> 2146 | G5: =SUMIF(RawData[Product_Category],"Office Supplies",RawData[Revenue]) -> 498079.2 | H5: =SUMIF(RawData[Product_Category],"Office Supplies",RawData[Total_Cost]) -> 360491.7 | I5: =SUMIF(RawData[Product_Category],"Office Supplies",RawData[Profit]) -> 137587.5 | J5: =I5/G5 -> 0.27623619 | L5: March | M5: =MONTH(L5&1) -> 3 | N5: =SUMPRODUCT(--(MONTH(RawData[Order_Date])= M5)) -> 263 | O5: =SUMPRODUCT((MONTH(RawData[Order_Date])=M5)*RawData[Quantity]) -> 806 | P5: =SUMPRODUCT((MONTH(RawData[Order_Date])=M5)*RawData[Revenue]) -> 11872561 | Q5: =SUMPRODUCT((MONTH(RawData[Order_Date])=M5)*RawData[Profit]) -> 1756436.4 | R5: =IFERROR(Q5/P5,0) -> 0.14794082 | T5: Furniture | U5: Regular | V5: =COUNTIFS(RawData[Product_Category],"Furniture",RawData[Order_Date],"<"&DATE(2025,11,1)) -> 688 | W5: =SUMIFS(RawData[Quantity],RawData[Product_Category],"Furniture",RawData[Order_Date],"<"&DATE(2025,11,1)) -> 2037 | X5: =SUMIFS(RawData[Revenue],RawData[Product_Category],"Furniture",RawData[Order_Date],"<"&DATE(2025,11,1)) -> 42783269 | Y5: =SUMIFS(RawData[Profit],RawData[Product_Category],"Furniture",RawData[Order_Date],"<"&DATE(2025,11,1)) -> 7242049.8 | Z5: =Y5/X5 -> 0.16927294 | AA5: ="₹"&TEXT(Category_and_Seasonal_Analysis[[#This Row],[Revenue]]/10000000,"0.00")&" Cr" -> ₹4.28 Cr | AB5: ="₹"&TEXT(Category_and_Seasonal_Analysis[[#This Row],[Profit]]/100000,"0.00")&" L" -> ₹72.42 L | AD5: Tablet | AE5: Electronics | AF5: =COUNTIF(RawData[Product_Name],AD5) -> 147 | AG5: =SUMIF(RawData[Product_Name],AD5,RawData[Quantity]) -> 439 | AH5: =SUMIF(RawData[Product_Name],AD5,RawData[Revenue]) -> 11092822 | AI5: =SUMIF(RawData[Product_Name],AD5,RawData[Profit]) -> 831569.76 | AJ5: =AI5/AH5 -> 0.074964674 | AL5: C0003 | AM5: Anjali Bose | AN5: =COUNTIF(RawData[Customer_ID],AL5) -> 5 | AO5: =SUMIF(RawData[Customer_ID],AL5,RawData[Quantity]) -> 19 | AP5: =SUMIF(RawData[Customer_ID],AL5,RawData[Revenue]) -> 403024.2 | AQ5: =SUMIF(RawData[Customer_ID],AL5,RawData[Profit]) -> 49883.3 | AR5: =IF(AN5=0,0,AP5/AN5) -> 80604.84 | AS5: =IF(AN5=1,"One-time",IF(AN5<=4,"Occasional",IF(AN5<=8,"Loyal","Review"))) -> Loyal | AU5: Loyal | AV5: =COUNTIF(Customer_Analysis[Customer Type],AU5) -> 221 | AW5: =SUMIF(Customer_Analysis[Customer Type],AU5,Customer_Analysis[Orders]) -> 1255 | AX5: =SUMIF(Customer_Analysis[Customer Type],AU5,Customer_Analysis[Units Sold]) -> 3802 | AY5: =SUMIF(Customer_Analysis[Customer Type],AU5,Customer_Analysis[Revenue]) -> 52523828 | AZ5: =SUMIF(Customer_Analysis[Customer Type],AU5,Customer_Analysis[Profit]) -> 7267728.5 | BA5: =AZ5/AY5 -> 0.13837012 | BB5: =AY5/AV5 -> 237664.38 | BC5: =AZ5/AV5 -> 32885.649 | BD5: =AW5/AV5 -> 5.678733 | BE5: ="₹"&TEXT(Customer_Segment_Analysis[[#This Row],[Revenue]]/10000000,"0.00")&" Cr" -> ₹5.25 Cr | BG5: 3 | BH5: C0279 | BI5: Manav Rao | BJ5: 5 | BK5: 613493.55 | BL5: 85385.9 | BN5: 3 | BO5: C0279 | BP5: Manav Rao | BQ5: 5 | BR5: 613493.55 | BS5: 85385.9 | BU5: In-Store | BV5: =COUNTIF(RawData[Sales_Channel],BU5) -> 1660 | BW5: =SUMIF(RawData[Sales_Channel],BU5,RawData[Quantity]) -> 5083 | BX5: =SUMIF(RawData[Sales_Channel],BU5,RawData[Revenue]) -> 70213180 | BY5: =SUMIF(RawData[Sales_Channel],BU5,RawData[Profit]) -> 9582905.5 | BZ5: =BY5/BX5 -> 0.136483 | CA5: ="₹"&TEXT(Sales_Channel_Analysis[[#This Row],[Revenue]]/10000000,"0.00")&" Cr" -> ₹7.02 Cr | CC5: Debit Card | CD5: =COUNTIF(RawData[Payment_Mode],CC5) -> 638 | CE5: =SUMIF(RawData[Payment_Mode],CC5,RawData[Quantity]) -> 1933 | CF5: =SUMIF(RawData[Payment_Mode],CC5,RawData[Revenue]) -> 27155932 | CG5: =SUMIF(RawData[Payment_Mode],CC5,RawData[Profit]) -> 3724089.7 | CH5: =CG5/CF5 -> 0.13713724 | CI5: ="₹"&TEXT(Payment_Mode_Analysis[[#This Row],[Revenue]]/10000000,"0.00")&" Cr" -> ₹2.72 Cr | CK5: S003 | CL5: Rahul Sharma | CM5: =COUNTIF(RawData[Salesperson_ID],CK5) -> 303 | CN5: =SUMIF(RawData[Salesperson_ID],CK5,RawData[Quantity]) -> 932 | CO5: =SUMIF(RawData[Salesperson_ID],CK5,RawData[Revenue]) -> 10613170 | CP5: =SUMIF(RawData[Salesperson_ID],CK5,RawData[Profit]) -> 1477921.4 | CQ5: =CP5/CO5 -> 0.13925353 | CR5: =IF(CM5=0,0,CO5/CM5) -> 35026.964 | CS5: ="₹"&TEXT(Table29[[#This Row],[Revenue]]/10000000,"0.00")&" Cr" -> ₹1.06 Cr | CU5: Ahmedabad | CV5: West | CW5: =COUNTIF(RawData[City],CU5) -> 205 | CX5: =SUMIF(RawData[City],CU5,RawData[Quantity]) -> 609 | CY5: =SUMIF(RawData[City],CU5,RawData[Revenue]) -> 8732321 | CZ5: =SUMIF(RawData[City],CU5,RawData[Profit]) -> 1189644.5 | DA5: =CZ5/CY5 -> 0.13623463 | DC5: East | DD5: =SUMIF(City_Analysis[Region],DC5,City_Analysis[Orders]) -> 269 | DE5: =SUMIF(City_Analysis[Region],DC5,City_Analysis[Units Sold]) -> 792 | DF5: =SUMIF(City_Analysis[Region],DC5,City_Analysis[Revenue]) -> 10920469 | DG5: =SUMIF(City_Analysis[Region],DC5,City_Analysis[Profit]) -> 1516997.4 | DH5: =IF(DF5=0,0,DG5/DF5) -> 0.13891321 | DI5: ="₹"&TEXT(Region_Analysis[[#This Row],[Revenue]]/10000000,"0.00")&" Cr" -> ₹1.09 Cr | DK5: November | DL5: Office Supplies | DM5: =SUMIFS(RawData[Revenue],RawData[Product_Category],DL5, RawData[Order_Date],">="&DATE(2025,11,1),RawData[Order_Date],"<"&DATE(2025,12,1)) -> 41029.5 | DN5: =SUMIFS(RawData[Profit],RawData[Product_Category],Profit_Drop_Analysis[[#This Row],[Category]], RawData[Order_Date],">="&DATE(2025,11,1),RawData[Order_Date],"<"&DATE(2025,12,1)) -> 11104.5 | DO5: =DN5/DM5 -> 0.27064673 | DQ5: Tablet | DR5: =SUMIFS(RawData[Revenue],RawData[Product_Name],DQ5, RawData[Order_Date],">="&DATE(2025,11,1),RawData[Order_Date],"<"&DATE(2025,12,1)) -> 702599.45 | DS5: =SUMIFS(RawData[Profit],RawData[Product_Name],DQ5, RawData[Order_Date],">="&DATE(2025,11,1),RawData[Order_Date],"<"&DATE(2025,12,1)) -> 1374.95 | DT5: =DS5/DR5 -> 0.0019569472 | DU5: =SUMIFS(RawData[Revenue],RawData[Product_Name],DQ5, RawData[Order_Date],">="&DATE(2025,12,1),RawData[Order_Date],"<"&DATE(2026,1,1)) -> 1507770.2 | DV5: =SUMIFS(RawData[Profit],RawData[Product_Name],DQ5, RawData[Order_Date],">="&DATE(2025,12,1),RawData[Order_Date],"<"&DATE(2026,1,1)) -> 11824.57 | DW5: =DV5/DU5 -> 0.007842422 | DY5: March | DZ5: =MONTH(DY5&1) -> 3 | EA5: =SUMPRODUCT(--(MONTH(RawData[Order_Date])= DZ5)) -> 263 | EB5: =SUMPRODUCT((MONTH(RawData[Order_Date])=DZ5)*RawData[Quantity]) -> 806 | EC5: =SUMPRODUCT((MONTH(RawData[Order_Date])=DZ5)*RawData[Revenue]) -> 11872561 | ED5: =SUMPRODUCT((MONTH(RawData[Order_Date])=DZ5)*RawData[Profit]) -> 1756436.4 | EE5: =IFERROR(ED5/EC5,0) -> 0.14794082 | EG5: Tablet | EH5: =VLOOKUP(EG5,Product_Analysis[[Product]:[Profit Margin]],7,FALSE) -> 0.074964674 | EI5: 0.0019569472 | EJ5: =AVERAGEIFS(RawData[Discount%],RawData[Product_Name],EG5,RawData[Order_Date],">="&DATE(2025,11,1),RawData[Order_Date],"<"&DATE(2025,12,1)) -> 14.545455 | EK5: 0.007842422 | EL5: =AVERAGEIFS(RawData[Discount%],RawData[Product_Name],EG5,RawData[Order_Date],">="&DATE(2025,12,1),RawData[Order_Date],"<"&DATE(2026,1,1)) -> 14.421053
A6: Total Quantity Sold | B6: =SUM(RawData[Quantity]) -> 9029 | L6: April | M6: =MONTH(L6&1) -> 4 | N6: =SUMPRODUCT(--(MONTH(RawData[Order_Date])= M6)) -> 258 | O6: =SUMPRODUCT((MONTH(RawData[Order_Date])=M6)*RawData[Quantity]) -> 756 | P6: =SUMPRODUCT((MONTH(RawData[Order_Date])=M6)*RawData[Revenue]) -> 10348640 | Q6: =SUMPRODUCT((MONTH(RawData[Order_Date])=M6)*RawData[Profit]) -> 1585968.6 | R6: =IFERROR(Q6/P6,0) -> 0.15325382 | T6: Furniture | U6: Festival | V6: =COUNTIFS(RawData[Product_Category],"Furniture",RawData[Order_Date],">="&DATE(2025,11,1)) -> 128 | W6: =SUMIFS(RawData[Quantity],RawData[Product_Category],"Furniture",RawData[Order_Date],">="&DATE(2025,11,1)) -> 386 | X6: =SUMIFS(RawData[Revenue],RawData[Product_Category],"Furniture",RawData[Order_Date],">="&DATE(2025,11,1)) -> 6935300.1 | Y6: =SUMIFS(RawData[Profit],RawData[Product_Category],"Furniture",RawData[Order_Date],">="&DATE(2025,11,1)) -> 555861.24 | Z6: =Y6/X6 -> 0.080149559 | AA6: ="₹"&TEXT(Category_and_Seasonal_Analysis[[#This Row],[Revenue]]/10000000,"0.00")&" Cr" -> ₹0.69 Cr | AB6: ="₹"&TEXT(Category_and_Seasonal_Analysis[[#This Row],[Profit]]/100000,"0.00")&" L" -> ₹5.56 L | AD6: Monitor | AE6: Electronics | AF6: =COUNTIF(RawData[Product_Name],AD6) -> 156 | AG6: =SUMIF(RawData[Product_Name],AD6,RawData[Quantity]) -> 459 | AH6: =SUMIF(RawData[Product_Name],AD6,RawData[Revenue]) -> 7016694.7 | AI6: =SUMIF(RawData[Product_Name],AD6,RawData[Profit]) -> 352418.64 | AJ6: =AI6/AH6 -> 0.050225734 | AL6: C0004 | AM6: Akash Kapoor | AN6: =COUNTIF(RawData[Customer_ID],AL6) -> 4 | AO6: =SUMIF(RawData[Customer_ID],AL6,RawData[Quantity]) -> 19 | AP6: =SUMIF(RawData[Customer_ID],AL6,RawData[Revenue]) -> 426610.65 | AQ6: =SUMIF(RawData[Customer_ID],AL6,RawData[Profit]) -> 65613.7 | AR6: =IF(AN6=0,0,AP6/AN6) -> 106652.66 | AS6: =IF(AN6=1,"One-time",IF(AN6<=4,"Occasional",IF(AN6<=8,"Loyal","Review"))) -> Occasional | AU6: Review | AV6: =COUNTIF(Customer_Analysis[Customer Type],AU6) -> 10 | AW6: =SUMIF(Customer_Analysis[Customer Type],AU6,Customer_Analysis[Orders]) -> 93 | AX6: =SUMIF(Customer_Analysis[Customer Type],AU6,Customer_Analysis[Units Sold]) -> 284 | AY6: =SUMIF(Customer_Analysis[Customer Type],AU6,Customer_Analysis[Revenue]) -> 3239528.1 | AZ6: =SUMIF(Customer_Analysis[Customer Type],AU6,Customer_Analysis[Profit]) -> 430379.46 | BA6: =AZ6/AY6 -> 0.13285251 | BB6: =AY6/AV6 -> 323952.82 | BC6: =AZ6/AV6 -> 43037.946 | BD6: =AW6/AV6 -> 9.3 | BE6: ="₹"&TEXT(Customer_Segment_Analysis[[#This Row],[Revenue]]/10000000,"0.00")&" Cr" -> ₹0.32 Cr | BG6: 4 | BH6: C0846 | BI6: Nikita Saxena | BJ6: 7 | BK6: 586628.8 | BL6: 89714.14 | BN6: 4 | BO6: C0316 | BP6: Nandini Fernandes | BQ6: 10 | BR6: 506960.31 | BS6: 83565.66 | BU6: total | BV6: =SUM(BV3:BV5) -> 3000 | BW6: =SUM(BW3:BW5) -> 9029 | BX6: =SUM(BX3:BX5) -> 1.2407907e+08 | BY6: =SUM(BY3:BY5) -> 17118773 | BZ6: =SUM(BZ3:BZ5) -> 0.41990667 | CA6: ="₹"&TEXT(Sales_Channel_Analysis[[#This Row],[Revenue]]/10000000,"0.00")&" Cr" -> ₹12.41 Cr | CC6: Cash | CD6: =COUNTIF(RawData[Payment_Mode],CC6) -> 307 | CE6: =SUMIF(RawData[Payment_Mode],CC6,RawData[Quantity]) -> 881 | CF6: =SUMIF(RawData[Payment_Mode],CC6,RawData[Revenue]) -> 11258890 | CG6: =SUMIF(RawData[Payment_Mode],CC6,RawData[Profit]) -> 1493053.4 | CH6: =CG6/CF6 -> 0.13261107 | CI6: ="₹"&TEXT(Payment_Mode_Analysis[[#This Row],[Revenue]]/10000000,"0.00")&" Cr" -> ₹1.13 Cr | CK6: S004 | CL6: Sneha Mehta | CM6: =COUNTIF(RawData[Salesperson_ID],CK6) -> 299 | CN6: =SUMIF(RawData[Salesperson_ID],CK6,RawData[Quantity]) -> 900 | CO6: =SUMIF(RawData[Salesperson_ID],CK6,RawData[Revenue]) -> 12620581 | CP6: =SUMIF(RawData[Salesperson_ID],CK6,RawData[Profit]) -> 1805729.8 | CQ6: =CP6/CO6 -> 0.14307818 | CR6: =IF(CM6=0,0,CO6/CM6) -> 42209.301 | CS6: ="₹"&TEXT(Table29[[#This Row],[Revenue]]/10000000,"0.00")&" Cr" -> ₹1.26 Cr | CU6: Indore | CV6: West | CW6: =COUNTIF(RawData[City],CU6) -> 272 | CX6: =SUMIF(RawData[City],CU6,RawData[Quantity]) -> 871 | CY6: =SUMIF(RawData[City],CU6,RawData[Revenue]) -> 13301066 | CZ6: =SUMIF(RawData[City],CU6,RawData[Profit]) -> 1834841.4 | DA6: =CZ6/CY6 -> 0.13794694 | DC6: West | DD6: =SUMIF(City_Analysis[Region],DC6,City_Analysis[Orders]) -> 1199 | DE6: =SUMIF(City_Analysis[Region],DC6,City_Analysis[Units Sold]) -> 3581 | DF6: =SUMIF(City_Analysis[Region],DC6,City_Analysis[Revenue]) -> 50096317 | DG6: =SUMIF(City_Analysis[Region],DC6,City_Analysis[Profit]) -> 6874817.9 | DH6: =IF(DF6=0,0,DG6/DF6) -> 0.137232 | DI6: ="₹"&TEXT(Region_Analysis[[#This Row],[Revenue]]/10000000,"0.00")&" Cr" -> ₹5.01 Cr | DK6: December | DL6: Electronics | DM6: =SUMIFS(RawData[Revenue],RawData[Product_Category],DL6, RawData[Order_Date],">="&DATE(2025,12,1),RawData[Order_Date],"<"&DATE(2026,1,1)) -> 5965907.6 | DN6: =SUMIFS(RawData[Profit],RawData[Product_Category],Profit_Drop_Analysis[[#This Row],[Category]], RawData[Order_Date],">="&DATE(2025,12,1),RawData[Order_Date],"<"&DATE(2026,1,1)) -> 280477.73 | DO6: =DN6/DM6 -> 0.047013422 | DQ6: Monitor | DR6: =SUMIFS(RawData[Revenue],RawData[Product_Name],DQ6, RawData[Order_Date],">="&DATE(2025,11,1),RawData[Order_Date],"<"&DATE(2025,12,1)) -> 501239.62 | DS6: =SUMIFS(RawData[Profit],RawData[Product_Name],DQ6, RawData[Order_Date],">="&DATE(2025,11,1),RawData[Order_Date],"<"&DATE(2025,12,1)) -> -6929.58 | DT6: =DS6/DR6 -> -0.013824885 | DU6: =SUMIFS(RawData[Revenue],RawData[Product_Name],DQ6, RawData[Order_Date],">="&DATE(2025,12,1),RawData[Order_Date],"<"&DATE(2026,1,1)) -> 725626.02 | DV6: =SUMIFS(RawData[Profit],RawData[Product_Name],DQ6, RawData[Order_Date],">="&DATE(2025,12,1),RawData[Order_Date],"<"&DATE(2026,1,1)) -> -14849.1 | DW6: =DV6/DU6 -> -0.020463847 | DY6: April | DZ6: =MONTH(DY6&1) -> 4 | EA6: =SUMPRODUCT(--(MONTH(RawData[Order_Date])= DZ6)) -> 258 | EB6: =SUMPRODUCT((MONTH(RawData[Order_Date])=DZ6)*RawData[Quantity]) -> 756 | EC6: =SUMPRODUCT((MONTH(RawData[Order_Date])=DZ6)*RawData[Revenue]) -> 10348640 | ED6: =SUMPRODUCT((MONTH(RawData[Order_Date])=DZ6)*RawData[Profit]) -> 1585968.6 | EE6: =IFERROR(ED6/EC6,0) -> 0.15325382 | EG6: Monitor | EH6: =VLOOKUP(EG6,Product_Analysis[[Product]:[Profit Margin]],7,FALSE) -> 0.050225734 | EI6: -0.013824885 | EJ6: =AVERAGEIFS(RawData[Discount%],RawData[Product_Name],EG6,RawData[Order_Date],">="&DATE(2025,11,1),RawData[Order_Date],"<"&DATE(2025,12,1)) -> 13.25 | EK6: -0.020463847 | EL6: =AVERAGEIFS(RawData[Discount%],RawData[Product_Name],EG6,RawData[Order_Date],">="&DATE(2025,12,1),RawData[Order_Date],"<"&DATE(2026,1,1)) -> 13.666667
A7: Earliest Order Date | B7: =MIN(RawData[Order_Date]) -> 45658 | L7: May | M7: =MONTH(L7&1) -> 5 | N7: =SUMPRODUCT(--(MONTH(RawData[Order_Date])= M7)) -> 229 | O7: =SUMPRODUCT((MONTH(RawData[Order_Date])=M7)*RawData[Quantity]) -> 674 | P7: =SUMPRODUCT((MONTH(RawData[Order_Date])=M7)*RawData[Revenue]) -> 8656122.3 | Q7: =SUMPRODUCT((MONTH(RawData[Order_Date])=M7)*RawData[Profit]) -> 1332230.5 | R7: =IFERROR(Q7/P7,0) -> 0.15390615 | T7: Office Supplies | U7: Regular | V7: =COUNTIFS(RawData[Product_Category],"Office Supplies",RawData[Order_Date],"<"&DATE(2025,11,1)) -> 597 | W7: =SUMIFS(RawData[Quantity],RawData[Product_Category],"Office Supplies",RawData[Order_Date],"<"&DATE(2025,11,1)) -> 1795 | X7: =SUMIFS(RawData[Revenue],RawData[Product_Category],"Office Supplies",RawData[Order_Date],"<"&DATE(2025,11,1)) -> 407947 | Y7: =SUMIFS(RawData[Profit],RawData[Product_Category],"Office Supplies",RawData[Order_Date],"<"&DATE(2025,11,1)) -> 113119 | Z7: =Y7/X7 -> 0.27728847 | AA7: ="₹"&TEXT(Category_and_Seasonal_Analysis[[#This Row],[Revenue]]/10000000,"0.00")&" Cr" -> ₹0.04 Cr | AB7: ="₹"&TEXT(Category_and_Seasonal_Analysis[[#This Row],[Profit]]/100000,"0.00")&" L" -> ₹1.13 L | AD7: Printer | AE7: Electronics | AF7: =COUNTIF(RawData[Product_Name],AD7) -> 129 | AG7: =SUMIF(RawData[Product_Name],AD7,RawData[Quantity]) -> 382 | AH7: =SUMIF(RawData[Product_Name],AD7,RawData[Revenue]) -> 4902068.5 | AI7: =SUMIF(RawData[Product_Name],AD7,RawData[Profit]) -> 700374.06 | AJ7: =AI7/AH7 -> 0.14287317 | AL7: C0005 | AM7: Bhavya Kapoor | AN7: =COUNTIF(RawData[Customer_ID],AL7) -> 2 | AO7: =SUMIF(RawData[Customer_ID],AL7,RawData[Quantity]) -> 8 | AP7: =SUMIF(RawData[Customer_ID],AL7,RawData[Revenue]) -> 116842.69 | AQ7: =SUMIF(RawData[Customer_ID],AL7,RawData[Profit]) -> 19273.66 | AR7: =IF(AN7=0,0,AP7/AN7) -> 58421.345 | AS7: =IF(AN7=1,"One-time",IF(AN7<=4,"Occasional",IF(AN7<=8,"Loyal","Review"))) -> Occasional | AU7: total | AV7: =SUM(AV3:AV6) -> 900 | AW7: =SUM(AW3:AW6) -> 3000 | AX7: =SUM(AX3:AX6) -> 9029 | AY7: =SUM(AY3:AY6) -> 1.2407907e+08 | AZ7: =SUM(AZ3:AZ6) -> 17118773 | BA7: =AZ7/AY7 -> 0.13796665 | BG7: 5 | BH7: C0749 | BI7: Rohit Menon | BJ7: 6 | BK7: 582797.79 | BL7: 73254.61 | BN7: 5 | BO7: C0793 | BP7: Charu Parmar | BQ7: 6 | BR7: 569033.95 | BS7: 83347.99 | CC7: Net Banking | CD7: =COUNTIF(RawData[Payment_Mode],CC7) -> 152 | CE7: =SUMIF(RawData[Payment_Mode],CC7,RawData[Quantity]) -> 460 | CF7: =SUMIF(RawData[Payment_Mode],CC7,RawData[Revenue]) -> 6334631.4 | CG7: =SUMIF(RawData[Payment_Mode],CC7,RawData[Profit]) -> 911660.63 | CH7: =CG7/CF7 -> 0.14391692 | CI7: ="₹"&TEXT(Payment_Mode_Analysis[[#This Row],[Revenue]]/10000000,"0.00")&" Cr" -> ₹0.63 Cr | CK7: S005 | CL7: Vivek Gupta | CM7: =COUNTIF(RawData[Salesperson_ID],CK7) -> 325 | CN7: =SUMIF(RawData[Salesperson_ID],CK7,RawData[Quantity]) -> 1002 | CO7: =SUMIF(RawData[Salesperson_ID],CK7,RawData[Revenue]) -> 14075883 | CP7: =SUMIF(RawData[Salesperson_ID],CK7,RawData[Profit]) -> 1954828.8 | CQ7: =CP7/CO7 -> 0.13887788 | CR7: =IF(CM7=0,0,CO7/CM7) -> 43310.41 | CS7: ="₹"&TEXT(Table29[[#This Row],[Revenue]]/10000000,"0.00")&" Cr" -> ₹1.41 Cr | CU7: Nagpur | CV7: West | CW7: =COUNTIF(RawData[City],CU7) -> 265 | CX7: =SUMIF(RawData[City],CU7,RawData[Quantity]) -> 754 | CY7: =SUMIF(RawData[City],CU7,RawData[Revenue]) -> 10790921 | CZ7: =SUMIF(RawData[City],CU7,RawData[Profit]) -> 1471183.3 | DA7: =CZ7/CY7 -> 0.13633528 | DD7: =SUM(DD3:DD6) -> 3000 | DE7: =SUM(DE3:DE6) -> 9029 | DF7: =SUM(DF3:DF6) -> 1.2407907e+08 | DG7: =SUM(DG3:DG6) -> 17118773 | DK7: December | DL7: Furniture | DM7: =SUMIFS(RawData[Revenue],RawData[Product_Category],Profit_Drop_Analysis[[#This Row],[Category]], RawData[Order_Date],">="&DATE(2025,12,1),RawData[Order_Date],"<"&DATE(2026,1,1)) -> 3250319 | DN7: =SUMIFS(RawData[Profit],RawData[Product_Category],Profit_Drop_Analysis[[#This Row],[Category]], RawData[Order_Date],">="&DATE(2025,12,1),RawData[Order_Date],"<"&DATE(2026,1,1)) -> 271803.43 | DO7: =DN7/DM7 -> 0.083623618 | DQ7: Printer | DR7: =SUMIFS(RawData[Revenue],RawData[Product_Name],DQ7, RawData[Order_Date],">="&DATE(2025,11,1),RawData[Order_Date],"<"&DATE(2025,12,1)) -> 310727.4 | DS7: =SUMIFS(RawData[Profit],RawData[Product_Name],DQ7, RawData[Order_Date],">="&DATE(2025,11,1),RawData[Order_Date],"<"&DATE(2025,12,1)) -> 24748.2 | DT7: =DS7/DR7 -> 0.079646018 | DU7: =SUMIFS(RawData[Revenue],RawData[Product_Name],DQ7, RawData[Order_Date],">="&DATE(2025,12,1),RawData[Order_Date],"<"&DATE(2026,1,1)) -> 287904.06 | DV7: =SUMIFS(RawData[Profit],RawData[Product_Name],DQ7, RawData[Order_Date],">="&DATE(2025,12,1),RawData[Order_Date],"<"&DATE(2026,1,1)) -> 23923.26 | DW7: =DV7/DU7 -> 0.083094556 | DY7: May | DZ7: =MONTH(DY7&1) -> 5 | EA7: =SUMPRODUCT(--(MONTH(RawData[Order_Date])= DZ7)) -> 229 | EB7: =SUMPRODUCT((MONTH(RawData[Order_Date])=DZ7)*RawData[Quantity]) -> 674 | EC7: =SUMPRODUCT((MONTH(RawData[Order_Date])=DZ7)*RawData[Revenue]) -> 8656122.3 | ED7: =SUMPRODUCT((MONTH(RawData[Order_Date])=DZ7)*RawData[Profit]) -> 1332230.5 | EE7: =IFERROR(ED7/EC7,0) -> 0.15390615 | EG7: Sofa | EH7: =VLOOKUP(EG7,Product_Analysis[[Product]:[Profit Margin]],7,FALSE) -> 0.15169884 | EI7: 0.071171421 | EJ7: =AVERAGEIFS(RawData[Discount%],RawData[Product_Name],EG7,RawData[Order_Date],">="&DATE(2025,11,1),RawData[Order_Date],"<"&DATE(2025,12,1)) -> 16.333333 | EK7: 8.16 | EL7: =AVERAGEIFS(RawData[Discount%],RawData[Product_Name],EG7,RawData[Order_Date],">="&DATE(2025,12,1),RawData[Order_Date],"<"&DATE(2026,1,1)) -> 14.916667
A8: Latest Order Date | B8: =MAX(RawData[Order_Date]) -> 46022 | L8: June | M8: =MONTH(L8&1) -> 6 | N8: =SUMPRODUCT(--(MONTH(RawData[Order_Date])= M8)) -> 236 | O8: =SUMPRODUCT((MONTH(RawData[Order_Date])=M8)*RawData[Quantity]) -> 720 | P8: =SUMPRODUCT((MONTH(RawData[Order_Date])=M8)*RawData[Revenue]) -> 10428620 | Q8: =SUMPRODUCT((MONTH(RawData[Order_Date])=M8)*RawData[Profit]) -> 1539638.1 | R8: =IFERROR(Q8/P8,0) -> 0.14763585 | T8: Office Supplies | U8: Festival | V8: =COUNTIFS(RawData[Product_Category],"Office Supplies",RawData[Order_Date],">="&DATE(2025,11,1)) -> 115 | W8: =SUMIFS(RawData[Quantity],RawData[Product_Category],"Office Supplies",RawData[Order_Date],">="&DATE(2025,11,1)) -> 351 | X8: =SUMIFS(RawData[Revenue],RawData[Product_Category],"Office Supplies",RawData[Order_Date],">="&DATE(2025,11,1)) -> 90132.2 | Y8: =SUMIFS(RawData[Profit],RawData[Product_Category],"Office Supplies",RawData[Order_Date],">="&DATE(2025,11,1)) -> 24468.5 | Z8: =Y8/X8 -> 0.27147346 | AA8: ="₹"&TEXT(Category_and_Seasonal_Analysis[[#This Row],[Revenue]]/10000000,"0.00")&" Cr" -> ₹0.01 Cr | AB8: ="₹"&TEXT(Category_and_Seasonal_Analysis[[#This Row],[Profit]]/100000,"0.00")&" L" -> ₹0.24 L | AD8: Smartwatch | AE8: Electronics | AF8: =COUNTIF(RawData[Product_Name],AD8) -> 165 | AG8: =SUMIF(RawData[Product_Name],AD8,RawData[Quantity]) -> 508 | AH8: =SUMIF(RawData[Product_Name],AD8,RawData[Revenue]) -> 4503000 | AI8: =SUMIF(RawData[Product_Name],AD8,RawData[Profit]) -> 1124800 | AJ8: =AI8/AH8 -> 0.24978903 | AL8: C0006 | AM8: Rudra Gupta | AN8: =COUNTIF(RawData[Customer_ID],AL8) -> 3 | AO8: =SUMIF(RawData[Customer_ID],AL8,RawData[Quantity]) -> 4 | AP8: =SUMIF(RawData[Customer_ID],AL8,RawData[Revenue]) -> 163266.32 | AQ8: =SUMIF(RawData[Customer_ID],AL8,RawData[Profit]) -> 18969.53 | AR8: =IF(AN8=0,0,AP8/AN8) -> 54422.107 | AS8: =IF(AN8=1,"One-time",IF(AN8<=4,"Occasional",IF(AN8<=8,"Loyal","Review"))) -> Occasional | BG8: 6 | BH8: C0793 | BI8: Charu Parmar | BJ8: 6 | BK8: 569033.95 | BL8: 83347.99 | BN8: 6 | BO8: C0012 | BP8: Trisha Jain | BQ8: 4 | BR8: 688035.24 | BS8: 83323.21 | CK8: S006 | CL8: Ananya Joshi | CM8: =COUNTIF(RawData[Salesperson_ID],CK8) -> 317 | CN8: =SUMIF(RawData[Salesperson_ID],CK8,RawData[Quantity]) -> 923 | CO8: =SUMIF(RawData[Salesperson_ID],CK8,RawData[Revenue]) -> 13496038 | CP8: =SUMIF(RawData[Salesperson_ID],CK8,RawData[Profit]) -> 1765422.1 | CQ8: =CP8/CO8 -> 0.1308104 | CR8: =IF(CM8=0,0,CO8/CM8) -> 42574.253 | CS8: ="₹"&TEXT(Table29[[#This Row],[Revenue]]/10000000,"0.00")&" Cr" -> ₹1.35 Cr | CU8: Delhi | CV8: North | CW8: =COUNTIF(RawData[City],CU8) -> 251 | CX8: =SUMIF(RawData[City],CU8,RawData[Quantity]) -> 777 | CY8: =SUMIF(RawData[City],CU8,RawData[Revenue]) -> 11014919 | CZ8: =SUMIF(RawData[City],CU8,RawData[Profit]) -> 1580572.9 | DA8: =CZ8/CY8 -> 0.14349384 | DK8: December | DL8: Office Supplies | DM8: =SUMIFS(RawData[Revenue],RawData[Product_Category],Profit_Drop_Analysis[[#This Row],[Category]], RawData[Order_Date],">="&DATE(2025,12,1),RawData[Order_Date],"<"&DATE(2026,1,1)) -> 49102.7 | DN8: =SUMIFS(RawData[Profit],RawData[Product_Category],Profit_Drop_Analysis[[#This Row],[Category]], RawData[Order_Date],">="&DATE(2025,12,1),RawData[Order_Date],"<"&DATE(2026,1,1)) -> 13364 | DO8: =DN8/DM8 -> 0.27216426 | DQ8: Smartwatch | DR8: =SUMIFS(RawData[Revenue],RawData[Product_Name],DQ8, RawData[Order_Date],">="&DATE(2025,11,1),RawData[Order_Date],"<"&DATE(2025,12,1)) -> 230470 | DS8: =SUMIFS(RawData[Profit],RawData[Product_Name],DQ8, RawData[Order_Date],">="&DATE(2025,11,1),RawData[Order_Date],"<"&DATE(2025,12,1)) -> 44270 | DT8: =DS8/DR8 -> 0.19208574 | DU8: =SUMIFS(RawData[Revenue],RawData[Product_Name],DQ8, RawData[Order_Date],">="&DATE(2025,12,1),RawData[Order_Date],"<"&DATE(2026,1,1)) -> 354825 | DV8: =SUMIFS(RawData[Profit],RawData[Product_Name],DQ8, RawData[Order_Date],">="&DATE(2025,12,1),RawData[Order_Date],"<"&DATE(2026,1,1)) -> 68875 | DW8: =DV8/DU8 -> 0.19410977 | DY8: June | DZ8: =MONTH(DY8&1) -> 6 | EA8: =SUMPRODUCT(--(MONTH(RawData[Order_Date])= DZ8)) -> 236 | EB8: =SUMPRODUCT((MONTH(RawData[Order_Date])=DZ8)*RawData[Quantity]) -> 720 | EC8: =SUMPRODUCT((MONTH(RawData[Order_Date])=DZ8)*RawData[Revenue]) -> 10428620 | ED8: =SUMPRODUCT((MONTH(RawData[Order_Date])=DZ8)*RawData[Profit]) -> 1539638.1 | EE8: =IFERROR(ED8/EC8,0) -> 0.14763585 | EG8: Dining Table | EH8: =VLOOKUP(EG8,Product_Analysis[[Product]:[Profit Margin]],7,FALSE) -> 0.14197211 | EI8: 0.054940186 | EJ8: =AVERAGEIFS(RawData[Discount%],RawData[Product_Name],EG8,RawData[Order_Date],">="&DATE(2025,11,1),RawData[Order_Date],"<"&DATE(2025,12,1)) -> 17 | EK8: 0.059203811 | EL8: =AVERAGEIFS(RawData[Discount%],RawData[Product_Name],EG8,RawData[Order_Date],">="&DATE(2025,12,1),RawData[Order_Date],"<"&DATE(2026,1,1)) -> 15.5
A9: Total Revenue | B9: =SUM(RawData[Revenue]) -> 1.2407907e+08 | L9: July | M9: =MONTH(L9&1) -> 7 | N9: =SUMPRODUCT(--(MONTH(RawData[Order_Date])= M9)) -> 246 | O9: =SUMPRODUCT((MONTH(RawData[Order_Date])=M9)*RawData[Quantity]) -> 754 | P9: =SUMPRODUCT((MONTH(RawData[Order_Date])=M9)*RawData[Revenue]) -> 11213253 | Q9: =SUMPRODUCT((MONTH(RawData[Order_Date])=M9)*RawData[Profit]) -> 1653414.4 | R9: =IFERROR(Q9/P9,0) -> 0.1474518 | AD9: External Hard Drive | AE9: Electronics | AF9: =COUNTIF(RawData[Product_Name],AD9) -> 146 | AG9: =SUMIF(RawData[Product_Name],AD9,RawData[Quantity]) -> 474 | AH9: =SUMIF(RawData[Product_Name],AD9,RawData[Revenue]) -> 3027513 | AI9: =SUMIF(RawData[Product_Name],AD9,RawData[Profit]) -> 312915 | AJ9: =AI9/AH9 -> 0.10335711 | AL9: C0007 | AM9: Diya Choudhary | AN9: =COUNTIF(RawData[Customer_ID],AL9) -> 2 | AO9: =SUMIF(RawData[Customer_ID],AL9,RawData[Quantity]) -> 7 | AP9: =SUMIF(RawData[Customer_ID],AL9,RawData[Revenue]) -> 18424.5 | AQ9: =SUMIF(RawData[Customer_ID],AL9,RawData[Profit]) -> 5327 | AR9: =IF(AN9=0,0,AP9/AN9) -> 9212.25 | AS9: =IF(AN9=1,"One-time",IF(AN9<=4,"Occasional",IF(AN9<=8,"Loyal","Review"))) -> Occasional | AW9: =SUM(Top_10_customers_by_revenue[Revenue])/SUM(Customer_Analysis[Revenue]) -> 0.046139923 | BG9: 7 | BH9: C0331 | BI9: Priya Pawar | BJ9: 5 | BK9: 519493.96 | BL9: 59319.53 | BN9: 7 | BO9: C0663 | BP9: Diya Shetty | BQ9: 6 | BR9: 464198.71 | BS9: 79057.39 | CK9: S007 | CL9: Rohit Desai | CM9: =COUNTIF(RawData[Salesperson_ID],CK9) -> 309 | CN9: =SUMIF(RawData[Salesperson_ID],CK9,RawData[Quantity]) -> 948 | CO9: =SUMIF(RawData[Salesperson_ID],CK9,RawData[Revenue]) -> 13439275 | CP9: =SUMIF(RawData[Salesperson_ID],CK9,RawData[Profit]) -> 1868245.7 | CQ9: =CP9/CO9 -> 0.13901388 | CR9: =IF(CM9=0,0,CO9/CM9) -> 43492.799 | CS9: ="₹"&TEXT(Table29[[#This Row],[Revenue]]/10000000,"0.00")&" Cr" -> ₹1.34 Cr | CU9: Jaipur | CV9: North | CW9: =COUNTIF(RawData[City],CU9) -> 245 | CX9: =SUMIF(RawData[City],CU9,RawData[Quantity]) -> 733 | CY9: =SUMIF(RawData[City],CU9,RawData[Revenue]) -> 9979978.3 | CZ9: =SUMIF(RawData[City],CU9,RawData[Profit]) -> 1382733.6 | DA9: =CZ9/CY9 -> 0.13855076 | DQ9: External Hard Drive | DR9: =SUMIFS(RawData[Revenue],RawData[Product_Name],DQ9, RawData[Order_Date],">="&DATE(2025,11,1),RawData[Order_Date],"<"&DATE(2025,12,1)) -> 260751 | DS9: =SUMIFS(RawData[Profit],RawData[Product_Name],DQ9, RawData[Order_Date],">="&DATE(2025,11,1),RawData[Order_Date],"<"&DATE(2025,12,1)) -> 8763 | DT9: =DS9/DR9 -> 0.033606774 | DU9: =SUMIFS(RawData[Revenue],RawData[Product_Name],DQ9, RawData[Order_Date],">="&DATE(2025,12,1),RawData[Order_Date],"<"&DATE(2026,1,1)) -> 202929 | DV9: =SUMIFS(RawData[Profit],RawData[Product_Name],DQ9, RawData[Order_Date],">="&DATE(2025,12,1),RawData[Order_Date],"<"&DATE(2026,1,1)) -> 8211 | DW9: =DV9/DU9 -> 0.040462428 | DY9: July | DZ9: =MONTH(DY9&1) -> 7 | EA9: =SUMPRODUCT(--(MONTH(RawData[Order_Date])= DZ9)) -> 246 | EB9: =SUMPRODUCT((MONTH(RawData[Order_Date])=DZ9)*RawData[Quantity]) -> 754 | EC9: =SUMPRODUCT((MONTH(RawData[Order_Date])=DZ9)*RawData[Revenue]) -> 11213253 | ED9: =SUMPRODUCT((MONTH(RawData[Order_Date])=DZ9)*RawData[Profit]) -> 1653414.4 | EE9: =IFERROR(ED9/EC9,0) -> 0.1474518 | EG9: Wardrobe | EH9: =VLOOKUP(EG9,Product_Analysis[[Product]:[Profit Margin]],7,FALSE) -> 0.13690553 | EI9: 3.75 | EJ9: =AVERAGEIFS(RawData[Discount%],RawData[Product_Name],EG9,RawData[Order_Date],">="&DATE(2025,11,1),RawData[Order_Date],"<"&DATE(2025,12,1)) -> 16.75 | EK9: 0.056300268 | EL9: =AVERAGEIFS(RawData[Discount%],RawData[Product_Name],EG9,RawData[Order_Date],">="&DATE(2025,12,1),RawData[Order_Date],"<"&DATE(2026,1,1)) -> 15.125
A10: Total Cost | B10: =SUM(RawData[Total_Cost]) -> 1.0696029e+08 | L10: August | M10: =MONTH(L10&1) -> 8 | N10: =SUMPRODUCT(--(MONTH(RawData[Order_Date])= M10)) -> 246 | O10: =SUMPRODUCT((MONTH(RawData[Order_Date])=M10)*RawData[Quantity]) -> 738 | P10: =SUMPRODUCT((MONTH(RawData[Order_Date])=M10)*RawData[Revenue]) -> 10899166 | Q10: =SUMPRODUCT((MONTH(RawData[Order_Date])=M10)*RawData[Profit]) -> 1601285.8 | R10: =IFERROR(Q10/P10,0) -> 0.1469182 | AD10: Earbuds | AE10: Electronics | AF10: =COUNTIF(RawData[Product_Name],AD10) -> 126 | AG10: =SUMIF(RawData[Product_Name],AD10,RawData[Quantity]) -> 366 | AH10: =SUMIF(RawData[Product_Name],AD10,RawData[Revenue]) -> 1221138.5 | AI10: =SUMIF(RawData[Product_Name],AD10,RawData[Profit]) -> 367077.5 | AJ10: =AI10/AH10 -> 0.30060268 | AL10: C0008 | AM10: Adarsh Verma | AN10: =COUNTIF(RawData[Customer_ID],AL10) -> 3 | AO10: =SUMIF(RawData[Customer_ID],AL10,RawData[Quantity]) -> 8 | AP10: =SUMIF(RawData[Customer_ID],AL10,RawData[Revenue]) -> 40020.05 | AQ10: =SUMIF(RawData[Customer_ID],AL10,RawData[Profit]) -> 10503.25 | AR10: =IF(AN10=0,0,AP10/AN10) -> 13340.017 | AS10: =IF(AN10=1,"One-time",IF(AN10<=4,"Occasional",IF(AN10<=8,"Loyal","Review"))) -> Occasional | BG10: 8 | BH10: C0296 | BI10: Kunal Kaur | BJ10: 7 | BK10: 513962.99 | BL10: 88176.92 | BN10: 8 | BO10: C0681 | BP10: Radhika Chatterjee | BQ10: 7 | BR10: 427904.55 | BS10: 74736.75 | CK10: S008 | CL10: Kavya Iyer | CM10: =COUNTIF(RawData[Salesperson_ID],CK10) -> 305 | CN10: =SUMIF(RawData[Salesperson_ID],CK10,RawData[Quantity]) -> 926 | CO10: =SUMIF(RawData[Salesperson_ID],CK10,RawData[Revenue]) -> 14729427 | CP10: =SUMIF(RawData[Salesperson_ID],CK10,RawData[Profit]) -> 2074756.4 | CQ10: =CP10/CO10 -> 0.14085792 | CR10: =IF(CM10=0,0,CO10/CM10) -> 48293.203 | CS10: ="₹"&TEXT(Table29[[#This Row],[Revenue]]/10000000,"0.00")&" Cr" -> ₹1.47 Cr | CU10: Lucknow | CV10: North | CW10: =COUNTIF(RawData[City],CU10) -> 253 | CX10: =SUMIF(RawData[City],CU10,RawData[Quantity]) -> 761 | CY10: =SUMIF(RawData[City],CU10,RawData[Revenue]) -> 10226360 | CZ10: =SUMIF(RawData[City],CU10,RawData[Profit]) -> 1381784.5 | DA10: =CZ10/CY10 -> 0.13511987 | DQ10: Earbuds | DR10: =SUMIFS(RawData[Revenue],RawData[Product_Name],DQ10, RawData[Order_Date],">="&DATE(2025,11,1),RawData[Order_Date],"<"&DATE(2025,12,1)) -> 110248.9 | DS10: =SUMIFS(RawData[Profit],RawData[Product_Name],DQ10, RawData[Order_Date],">="&DATE(2025,11,1),RawData[Order_Date],"<"&DATE(2025,12,1)) -> 26242.9 | DT10: =DS10/DR10 -> 0.23803321 | DU10: =SUMIFS(RawData[Revenue],RawData[Product_Name],DQ10, RawData[Order_Date],">="&DATE(2025,12,1),RawData[Order_Date],"<"&DATE(2026,1,1)) -> 78010.7 | DV10: =SUMIFS(RawData[Profit],RawData[Product_Name],DQ10, RawData[Order_Date],">="&DATE(2025,12,1),RawData[Order_Date],"<"&DATE(2026,1,1)) -> 19673.2 | DW10: =DV10/DU10 -> 0.25218592 | DY10: August | DZ10: =MONTH(DY10&1) -> 8 | EA10: =SUMPRODUCT(--(MONTH(RawData[Order_Date])= DZ10)) -> 246 | EB10: =SUMPRODUCT((MONTH(RawData[Order_Date])=DZ10)*RawData[Quantity]) -> 738 | EC10: =SUMPRODUCT((MONTH(RawData[Order_Date])=DZ10)*RawData[Revenue]) -> 10899166 | ED10: =SUMPRODUCT((MONTH(RawData[Order_Date])=DZ10)*RawData[Profit]) -> 1601285.8 | EE10: =IFERROR(ED10/EC10,0) -> 0.1469182
A11: Total Profit | B11: =SUM(RawData[Profit]) -> 17118773 | L11: September | M11: =MONTH(L11&1) -> 9 | N11: =SUMPRODUCT(--(MONTH(RawData[Order_Date])= M11)) -> 252 | O11: =SUMPRODUCT((MONTH(RawData[Order_Date])=M11)*RawData[Quantity]) -> 762 | P11: =SUMPRODUCT((MONTH(RawData[Order_Date])=M11)*RawData[Revenue]) -> 10035486 | Q11: =SUMPRODUCT((MONTH(RawData[Order_Date])=M11)*RawData[Profit]) -> 1510084 | R11: =IFERROR(Q11/P11,0) -> 0.15047442 | AD11: Keyboard | AE11: Electronics | AF11: =COUNTIF(RawData[Product_Name],AD11) -> 149 | AG11: =SUMIF(RawData[Product_Name],AD11,RawData[Quantity]) -> 431 | AH11: =SUMIF(RawData[Product_Name],AD11,RawData[Revenue]) -> 658581 | AI11: =SUMIF(RawData[Product_Name],AD11,RawData[Profit]) -> 231891 | AJ11: =AI11/AH11 -> 0.35210703 | AL11: C0009 | AM11: Krish Gupta | AN11: =COUNTIF(RawData[Customer_ID],AL11) -> 3 | AO11: =SUMIF(RawData[Customer_ID],AL11,RawData[Quantity]) -> 13 | AP11: =SUMIF(RawData[Customer_ID],AL11,RawData[Revenue]) -> 366981.94 | AQ11: =SUMIF(RawData[Customer_ID],AL11,RawData[Profit]) -> 38469.24 | AR11: =IF(AN11=0,0,AP11/AN11) -> 122327.31 | AS11: =IF(AN11=1,"One-time",IF(AN11<=4,"Occasional",IF(AN11<=8,"Loyal","Review"))) -> Occasional | BG11: 9 | BH11: C0316 | BI11: Nandini Fernandes | BJ11: 10 | BK11: 506960.31 | BL11: 83565.66 | BN11: 9 | BO11: C0749 | BP11: Rohit Menon | BQ11: 6 | BR11: 582797.79 | BS11: 73254.61 | CK11: S009 | CL11: Aditya Singh | CM11: =COUNTIF(RawData[Salesperson_ID],CK11) -> 281 | CN11: =SUMIF(RawData[Salesperson_ID],CK11,RawData[Quantity]) -> 850 | CO11: =SUMIF(RawData[Salesperson_ID],CK11,RawData[Revenue]) -> 11373643 | CP11: =SUMIF(RawData[Salesperson_ID],CK11,RawData[Profit]) -> 1570242 | CQ11: =CP11/CO11 -> 0.13805973 | CR11: =IF(CM11=0,0,CO11/CM11) -> 40475.596 | CS11: ="₹"&TEXT(Table29[[#This Row],[Revenue]]/10000000,"0.00")&" Cr" -> ₹1.14 Cr | CU11: Bengaluru | CV11: South | CW11: =COUNTIF(RawData[City],CU11) -> 242 | CX11: =SUMIF(RawData[City],CU11,RawData[Quantity]) -> 759 | CY11: =SUMIF(RawData[City],CU11,RawData[Revenue]) -> 11141384 | CZ11: =SUMIF(RawData[City],CU11,RawData[Profit]) -> 1452416.1 | DA11: =CZ11/CY11 -> 0.13036226 | DQ11: Keyboard | DR11: =SUMIFS(RawData[Revenue],RawData[Product_Name],DQ11, RawData[Order_Date],">="&DATE(2025,11,1),RawData[Order_Date],"<"&DATE(2025,12,1)) -> 67534.5 | DS11: =SUMIFS(RawData[Profit],RawData[Product_Name],DQ11, RawData[Order_Date],">="&DATE(2025,11,1),RawData[Order_Date],"<"&DATE(2025,12,1)) -> 21004.5 | DT11: =DS11/DR11 -> 0.31101881 | DU11: =SUMIFS(RawData[Revenue],RawData[Product_Name],DQ11, RawData[Order_Date],">="&DATE(2025,12,1),RawData[Order_Date],"<"&DATE(2026,1,1)) -> 36514.5 | DV11: =SUMIFS(RawData[Profit],RawData[Product_Name],DQ11, RawData[Order_Date],">="&DATE(2025,12,1),RawData[Order_Date],"<"&DATE(2026,1,1)) -> 10774.5 | DW11: =DV11/DU11 -> 0.29507456 | DY11: September | DZ11: =MONTH(DY11&1) -> 9 | EA11: =SUMPRODUCT(--(MONTH(RawData[Order_Date])= DZ11)) -> 252 | EB11: =SUMPRODUCT((MONTH(RawData[Order_Date])=DZ11)*RawData[Quantity]) -> 762 | EC11: =SUMPRODUCT((MONTH(RawData[Order_Date])=DZ11)*RawData[Revenue]) -> 10035486 | ED11: =SUMPRODUCT((MONTH(RawData[Order_Date])=DZ11)*RawData[Profit]) -> 1510084 | EE11: =IFERROR(ED11/EC11,0) -> 0.15047442
A12: Average Order Value | B12: =SUM(RawData[Revenue])/COUNTA(RawData[Order_ID]) -> 41359.689 | L12: October | M12: =MONTH(L12&1) -> 10 | N12: =SUMPRODUCT(--(MONTH(RawData[Order_Date])= M12)) -> 270 | O12: =SUMPRODUCT((MONTH(RawData[Order_Date])=M12)*RawData[Quantity]) -> 814 | P12: =SUMPRODUCT((MONTH(RawData[Order_Date])=M12)*RawData[Revenue]) -> 11273307 | Q12: =SUMPRODUCT((MONTH(RawData[Order_Date])=M12)*RawData[Profit]) -> 1741041.4 | R12: =IFERROR(Q12/P12,0) -> 0.15443928 | AD12: Mouse | AE12: Electronics | AF12: =COUNTIF(RawData[Product_Name],AD12) -> 139 | AG12: =SUMIF(RawData[Product_Name],AD12,RawData[Quantity]) -> 426 | AH12: =SUMIF(RawData[Product_Name],AD12,RawData[Revenue]) -> 433587 | AI12: =SUMIF(RawData[Product_Name],AD12,RawData[Profit]) -> 128997 | AJ12: =AI12/AH12 -> 0.29751123 | AL12: C0010 | AM12: Isha Singh | AN12: =COUNTIF(RawData[Customer_ID],AL12) -> 3 | AO12: =SUMIF(RawData[Customer_ID],AL12,RawData[Quantity]) -> 8 | AP12: =SUMIF(RawData[Customer_ID],AL12,RawData[Revenue]) -> 33153.4 | AQ12: =SUMIF(RawData[Customer_ID],AL12,RawData[Profit]) -> 6731.28 | AR12: =IF(AN12=0,0,AP12/AN12) -> 11051.133 | AS12: =IF(AN12=1,"One-time",IF(AN12<=4,"Occasional",IF(AN12<=8,"Loyal","Review"))) -> Occasional | BG12: 10 | BH12: C0072 | BI12: Vivaan Saxena | BJ12: 7 | BK12: 505946.16 | BL12: 62247.41 | BN12: 10 | BO12: C0833 | BP12: Charu Solanki | BQ12: 6 | BR12: 476531.68 | BS12: 70147.1 | CK12: S010 | CL12: Neha Verma | CM12: =COUNTIF(RawData[Salesperson_ID],CK12) -> 266 | CN12: =SUMIF(RawData[Salesperson_ID],CK12,RawData[Quantity]) -> 833 | CO12: =SUMIF(RawData[Salesperson_ID],CK12,RawData[Revenue]) -> 10408077 | CP12: =SUMIF(RawData[Salesperson_ID],CK12,RawData[Profit]) -> 1439303.2 | CQ12: =CP12/CO12 -> 0.13828714 | CR12: =IF(CM12=0,0,CO12/CM12) -> 39128.108 | CS12: ="₹"&TEXT(Table29[[#This Row],[Revenue]]/10000000,"0.00")&" Cr" -> ₹1.04 Cr | CU12: Hyderabad | CV12: South | CW12: =COUNTIF(RawData[City],CU12) -> 267 | CX12: =SUMIF(RawData[City],CU12,RawData[Quantity]) -> 831 | CY12: =SUMIF(RawData[City],CU12,RawData[Revenue]) -> 11216201 | CZ12: =SUMIF(RawData[City],CU12,RawData[Profit]) -> 1548696.3 | DA12: =CZ12/CY12 -> 0.13807672 | DQ12: Mouse | DR12: =SUMIFS(RawData[Revenue],RawData[Product_Name],DQ12, RawData[Order_Date],">="&DATE(2025,11,1),RawData[Order_Date],"<"&DATE(2025,12,1)) -> 36091 | DS12: =SUMIFS(RawData[Profit],RawData[Product_Name],DQ12, RawData[Order_Date],">="&DATE(2025,11,1),RawData[Order_Date],"<"&DATE(2025,12,1)) -> 8921 | DT12: =DS12/DR12 -> 0.24718074 | DU12: =SUMIFS(RawData[Revenue],RawData[Product_Name],DQ12, RawData[Order_Date],">="&DATE(2025,12,1),RawData[Order_Date],"<"&DATE(2026,1,1)) -> 36179 | DV12: =SUMIFS(RawData[Profit],RawData[Product_Name],DQ12, RawData[Order_Date],">="&DATE(2025,12,1),RawData[Order_Date],"<"&DATE(2026,1,1)) -> 8294 | DW12: =DV12/DU12 -> 0.22924901 | DY12: October | DZ12: =MONTH(DY12&1) -> 10 | EA12: =SUMPRODUCT(--(MONTH(RawData[Order_Date])= DZ12)) -> 270 | EB12: =SUMPRODUCT((MONTH(RawData[Order_Date])=DZ12)*RawData[Quantity]) -> 814 | EC12: =SUMPRODUCT((MONTH(RawData[Order_Date])=DZ12)*RawData[Revenue]) -> 11273307 | ED12: =SUMPRODUCT((MONTH(RawData[Order_Date])=DZ12)*RawData[Profit]) -> 1741041.4 | EE12: =IFERROR(ED12/EC12,0) -> 0.15443928
A13: Overall Profit Margin | B13: =SUM(RawData[Profit])/SUM(RawData[Revenue]) -> 0.13796665 | L13: November | M13: =MONTH(L13&1) -> 11 | N13: =SUMPRODUCT(--(MONTH(RawData[Order_Date])= M13)) -> 234 | O13: =SUMPRODUCT((MONTH(RawData[Order_Date])=M13)*RawData[Quantity]) -> 721 | P13: =SUMPRODUCT((MONTH(RawData[Order_Date])=M13)*RawData[Revenue]) -> 8908819.3 | Q13: =SUMPRODUCT((MONTH(RawData[Order_Date])=M13)*RawData[Profit]) -> 623120.47 | R13: =IFERROR(Q13/P13,0) -> 0.069944226 | AD13: Sofa | AE13: Furniture | AF13: =COUNTIF(RawData[Product_Name],AD13) -> 142 | AG13: =SUMIF(RawData[Product_Name],AD13,RawData[Quantity]) -> 427 | AH13: =SUMIF(RawData[Product_Name],AD13,RawData[Revenue]) -> 16882267 | AI13: =SUMIF(RawData[Product_Name],AD13,RawData[Profit]) -> 2561020.4 | AJ13: =AI13/AH13 -> 0.15169884 | AL13: C0011 | AM13: Swati Jain | AN13: =COUNTIF(RawData[Customer_ID],AL13) -> 5 | AO13: =SUMIF(RawData[Customer_ID],AL13,RawData[Quantity]) -> 9 | AP13: =SUMIF(RawData[Customer_ID],AL13,RawData[Revenue]) -> 122879.73 | AQ13: =SUMIF(RawData[Customer_ID],AL13,RawData[Profit]) -> 18158.23 | AR13: =IF(AN13=0,0,AP13/AN13) -> 24575.946 | AS13: =IF(AN13=1,"One-time",IF(AN13<=4,"Occasional",IF(AN13<=8,"Loyal","Review"))) -> Loyal | CM13: =SUM(CM3:CM12) -> 3000 | CN13: =SUM(CN3:CN12) -> 9029 | CO13: =SUM(CO3:CO12) -> 1.2407907e+08 | CP13: =SUM(CP3:CP12) -> 17118773 | CU13: Chennai | CV13: South | CW13: =COUNTIF(RawData[City],CU13) -> 274 | CX13: =SUMIF(RawData[City],CU13,RawData[Quantity]) -> 795 | CY13: =SUMIF(RawData[City],CU13,RawData[Revenue]) -> 9483438.8 | CZ13: =SUMIF(RawData[City],CU13,RawData[Profit]) -> 1380754.5 | DA13: =CZ13/CY13 -> 0.14559639 | DQ13: Sofa | DR13: =SUMIFS(RawData[Revenue],RawData[Product_Name],DQ13, RawData[Order_Date],">="&DATE(2025,11,1),RawData[Order_Date],"<"&DATE(2025,12,1)) -> 1552693.9 | DS13: =SUMIFS(RawData[Profit],RawData[Product_Name],DQ13, RawData[Order_Date],">="&DATE(2025,11,1),RawData[Order_Date],"<"&DATE(2025,12,1)) -> 110507.43 | DT13: =DS13/DR13 -> 0.071171421 | DU13: =SUMIFS(RawData[Revenue],RawData[Product_Name],DQ13, RawData[Order_Date],">="&DATE(2025,12,1),RawData[Order_Date],"<"&DATE(2026,1,1)) -> 1095614.5 | DV13: =SUMIFS(RawData[Profit],RawData[Product_Name],DQ13, RawData[Order_Date],">="&DATE(2025,12,1),RawData[Order_Date],"<"&DATE(2026,1,1)) -> 89437.92 | DW13: =DV13/DU13 -> 0.081632653 | DY13: November | DZ13: =MONTH(DY13&1) -> 11 | EA13: =SUMPRODUCT(--(MONTH(RawData[Order_Date])= DZ13)) -> 234 | EB13: =SUMPRODUCT((MONTH(RawData[Order_Date])=DZ13)*RawData[Quantity]) -> 721 | EC13: =SUMPRODUCT((MONTH(RawData[Order_Date])=DZ13)*RawData[Revenue]) -> 8908819.3 | ED13: =SUMPRODUCT((MONTH(RawData[Order_Date])=DZ13)*RawData[Profit]) -> 623120.47 | EE13: =IFERROR(ED13/EC13,0) -> 0.069944226
L14: December | M14: =MONTH(L14&1) -> 12 | N14: =SUMPRODUCT(--(MONTH(RawData[Order_Date])= M14)) -> 252 | O14: =SUMPRODUCT((MONTH(RawData[Order_Date])=M14)*RawData[Quantity]) -> 766 | P14: =SUMPRODUCT((MONTH(RawData[Order_Date])=M14)*RawData[Revenue]) -> 9265329.3 | Q14: =SUMPRODUCT((MONTH(RawData[Order_Date])=M14)*RawData[Profit]) -> 565645.16 | R14: =IFERROR(Q14/P14,0) -> 0.061049655 | AD14: Study Desk | AE14: Furniture | AF14: =COUNTIF(RawData[Product_Name],AD14) -> 130 | AG14: =SUMIF(RawData[Product_Name],AD14,RawData[Quantity]) -> 405 | AH14: =SUMIF(RawData[Product_Name],AD14,RawData[Revenue]) -> 4462908.1 | AI14: =SUMIF(RawData[Product_Name],AD14,RawData[Profit]) -> 818211.81 | AJ14: =AI14/AH14 -> 0.18333602 | AL14: C0012 | AM14: Trisha Jain | AN14: =COUNTIF(RawData[Customer_ID],AL14) -> 4 | AO14: =SUMIF(RawData[Customer_ID],AL14,RawData[Quantity]) -> 16 | AP14: =SUMIF(RawData[Customer_ID],AL14,RawData[Revenue]) -> 688035.24 | AQ14: =SUMIF(RawData[Customer_ID],AL14,RawData[Profit]) -> 83323.21 | AR14: =IF(AN14=0,0,AP14/AN14) -> 172008.81 | AS14: =IF(AN14=1,"One-time",IF(AN14<=4,"Occasional",IF(AN14<=8,"Loyal","Review"))) -> Occasional | CU14: Kolkata | CV14: East | CW14: =COUNTIF(RawData[City],CU14) -> 269 | CX14: =SUMIF(RawData[City],CU14,RawData[Quantity]) -> 792 | CY14: =SUMIF(RawData[City],CU14,RawData[Revenue]) -> 10920469 | CZ14: =SUMIF(RawData[City],CU14,RawData[Profit]) -> 1516997.4 | DA14: =CZ14/CY14 -> 0.13891321 | DQ14: Study Desk | DR14: =SUMIFS(RawData[Revenue],RawData[Product_Name],DQ14, RawData[Order_Date],">="&DATE(2025,11,1),RawData[Order_Date],"<"&DATE(2025,12,1)) -> 389727.52 | DS14: =SUMIFS(RawData[Profit],RawData[Product_Name],DQ14, RawData[Order_Date],">="&DATE(2025,11,1),RawData[Order_Date],"<"&DATE(2025,12,1)) -> 47756.02 | DT14: =DS14/DR14 -> 0.12253695 | DU14: =SUMIFS(RawData[Revenue],RawData[Product_Name],DQ14, RawData[Order_Date],">="&DATE(2025,12,1),RawData[Order_Date],"<"&DATE(2026,1,1)) -> 296495.29 | DV14: =SUMIFS(RawData[Profit],RawData[Product_Name],DQ14, RawData[Order_Date],">="&DATE(2025,12,1),RawData[Order_Date],"<"&DATE(2026,1,1)) -> 26517.79 | DW14: =DV14/DU14 -> 0.089437475 | DY14: December | DZ14: =MONTH(DY14&1) -> 12 | EA14: =SUMPRODUCT(--(MONTH(RawData[Order_Date])= DZ14)) -> 252 | EB14: =SUMPRODUCT((MONTH(RawData[Order_Date])=DZ14)*RawData[Quantity]) -> 766 | EC14: =SUMPRODUCT((MONTH(RawData[Order_Date])=DZ14)*RawData[Revenue]) -> 9265329.3 | ED14: =SUMPRODUCT((MONTH(RawData[Order_Date])=DZ14)*RawData[Profit]) -> 565645.16 | EE14: =IFERROR(ED14/EC14,0) -> 0.061049655
N15: =SUM(N3:N14) -> 3000 | O15: =SUM(O3:O14) -> 9029 | P15: =SUM(P3:P14) -> 1.2407907e+08 | Q15: =SUM(Q3:Q14) -> 17118773 | R15: =SUM(R3:R14) -> 1.6357807 | AD15: Office Chair | AE15: Furniture | AF15: =COUNTIF(RawData[Product_Name],AD15) -> 118 | AG15: =SUMIF(RawData[Product_Name],AD15,RawData[Quantity]) -> 363 | AH15: =SUMIF(RawData[Product_Name],AD15,RawData[Revenue]) -> 3009175.6 | AI15: =SUMIF(RawData[Product_Name],AD15,RawData[Profit]) -> 657196.97 | AJ15: =AI15/AH15 -> 0.21839768 | AL15: C0013 | AM15: Adarsh Malhotra | AN15: =COUNTIF(RawData[Customer_ID],AL15) -> 4 | AO15: =SUMIF(RawData[Customer_ID],AL15,RawData[Quantity]) -> 9 | AP15: =SUMIF(RawData[Customer_ID],AL15,RawData[Revenue]) -> 154449.33 | AQ15: =SUMIF(RawData[Customer_ID],AL15,RawData[Profit]) -> 25295.33 | AR15: =IF(AN15=0,0,AP15/AN15) -> 38612.333 | AS15: =IF(AN15=1,"One-time",IF(AN15<=4,"Occasional",IF(AN15<=8,"Loyal","Review"))) -> Occasional | CW15: =SUM(CW3:CW14) -> 3000 | CX15: =SUM(CX3:CX14) -> 9029 | CY15: =SUM(CY3:CY14) -> 1.2407907e+08 | CZ15: =SUM(CZ3:CZ14) -> 17118773 | DQ15: Office Chair | DR15: =SUMIFS(RawData[Revenue],RawData[Product_Name],DQ15, RawData[Order_Date],">="&DATE(2025,11,1),RawData[Order_Date],"<"&DATE(2025,12,1)) -> 236673.7 | DS15: =SUMIFS(RawData[Profit],RawData[Product_Name],DQ15, RawData[Order_Date],">="&DATE(2025,11,1),RawData[Order_Date],"<"&DATE(2025,12,1)) -> 35816.02 | DT15: =DS15/DR15 -> 0.1513308 | DU15: =SUMIFS(RawData[Revenue],RawData[Product_Name],DQ15, RawData[Order_Date],">="&DATE(2025,12,1),RawData[Order_Date],"<"&DATE(2026,1,1)) -> 279058.99 | DV15: =SUMIFS(RawData[Profit],RawData[Product_Name],DQ15, RawData[Order_Date],">="&DATE(2025,12,1),RawData[Order_Date],"<"&DATE(2026,1,1)) -> 45804.91 | DW15: =DV15/DU15 -> 0.1641406 | EA15: =SUM(EA3:EA14) -> 3000 | EB15: =SUM(EB3:EB14) -> 9029 | EC15: =SUM(EC3:EC14) -> 1.2407907e+08 | ED15: =SUM(ED3:ED14) -> 17118773 | EE15: =SUM(EE3:EE14) -> 1.6357807
AD16: Dining Table | AE16: Furniture | AF16: =COUNTIF(RawData[Product_Name],AD16) -> 136 | AG16: =SUMIF(RawData[Product_Name],AD16,RawData[Quantity]) -> 419 | AH16: =SUMIF(RawData[Product_Name],AD16,RawData[Revenue]) -> 10608564 | AI16: =SUMIF(RawData[Product_Name],AD16,RawData[Profit]) -> 1506120.2 | AJ16: =AI16/AH16 -> 0.14197211 | AL16: C0014 | AM16: Khushi Trivedi | AN16: =COUNTIF(RawData[Customer_ID],AL16) -> 1 | AO16: =SUMIF(RawData[Customer_ID],AL16,RawData[Quantity]) -> 3 | AP16: =SUMIF(RawData[Customer_ID],AL16,RawData[Revenue]) -> 1872 | AQ16: =SUMIF(RawData[Customer_ID],AL16,RawData[Profit]) -> 468 | AR16: =IF(AN16=0,0,AP16/AN16) -> 1872 | AS16: =IF(AN16=1,"One-time",IF(AN16<=4,"Occasional",IF(AN16<=8,"Loyal","Review"))) -> One-time | DQ16: Dining Table | DR16: =SUMIFS(RawData[Revenue],RawData[Product_Name],DQ16, RawData[Order_Date],">="&DATE(2025,11,1),RawData[Order_Date],"<"&DATE(2025,12,1)) -> 620652.43 | DS16: =SUMIFS(RawData[Profit],RawData[Product_Name],DQ16, RawData[Order_Date],">="&DATE(2025,11,1),RawData[Order_Date],"<"&DATE(2025,12,1)) -> 34098.76 | DT16: =DS16/DR16 -> 0.054940186 | DU16: =SUMIFS(RawData[Revenue],RawData[Product_Name],DQ16, RawData[Order_Date],">="&DATE(2025,12,1),RawData[Order_Date],"<"&DATE(2026,1,1)) -> 808195.61 | DV16: =SUMIFS(RawData[Profit],RawData[Product_Name],DQ16, RawData[Order_Date],">="&DATE(2025,12,1),RawData[Order_Date],"<"&DATE(2026,1,1)) -> 47848.26 | DW16: =DV16/DU16 -> 0.059203811
AD17: Wardrobe | AE17: Furniture | AF17: =COUNTIF(RawData[Product_Name],AD17) -> 146 | AG17: =SUMIF(RawData[Product_Name],AD17,RawData[Quantity]) -> 419 | AH17: =SUMIF(RawData[Product_Name],AD17,RawData[Revenue]) -> 12427452 | AI17: =SUMIF(RawData[Product_Name],AD17,RawData[Profit]) -> 1701386.8 | AJ17: =AI17/AH17 -> 0.13690553 | AL17: C0015 | AM17: Manav Nair | AN17: =COUNTIF(RawData[Customer_ID],AL17) -> 1 | AO17: =SUMIF(RawData[Customer_ID],AL17,RawData[Quantity]) -> 2 | AP17: =SUMIF(RawData[Customer_ID],AL17,RawData[Revenue]) -> 152 | AQ17: =SUMIF(RawData[Customer_ID],AL17,RawData[Profit]) -> 40 | AR17: =IF(AN17=0,0,AP17/AN17) -> 152 | AS17: =IF(AN17=1,"One-time",IF(AN17<=4,"Occasional",IF(AN17<=8,"Loyal","Review"))) -> One-time | DQ17: Wardrobe | DR17: =SUMIFS(RawData[Revenue],RawData[Product_Name],DQ17, RawData[Order_Date],">="&DATE(2025,11,1),RawData[Order_Date],"<"&DATE(2025,12,1)) -> 691498.39 | DS17: =SUMIFS(RawData[Profit],RawData[Product_Name],DQ17, RawData[Order_Date],">="&DATE(2025,11,1),RawData[Order_Date],"<"&DATE(2025,12,1)) -> 25919.19 | DT17: =DS17/DR17 -> 0.037482647 | DU17: =SUMIFS(RawData[Revenue],RawData[Product_Name],DQ17, RawData[Order_Date],">="&DATE(2025,12,1),RawData[Order_Date],"<"&DATE(2026,1,1)) -> 596781.35 | DV17: =SUMIFS(RawData[Profit],RawData[Product_Name],DQ17, RawData[Order_Date],">="&DATE(2025,12,1),RawData[Order_Date],"<"&DATE(2026,1,1)) -> 33598.95 | DW17: =DV17/DU17 -> 0.056300268
AD18: Bookshelf | AE18: Furniture | AF18: =COUNTIF(RawData[Product_Name],AD18) -> 144 | AG18: =SUMIF(RawData[Product_Name],AD18,RawData[Quantity]) -> 390 | AH18: =SUMIF(RawData[Product_Name],AD18,RawData[Revenue]) -> 2328201.8 | AI18: =SUMIF(RawData[Product_Name],AD18,RawData[Profit]) -> 553974.76 | AJ18: =AI18/AH18 -> 0.23794105 | AL18: C0016 | AM18: Kavya Rao | AN18: =COUNTIF(RawData[Customer_ID],AL18) -> 1 | AO18: =SUMIF(RawData[Customer_ID],AL18,RawData[Quantity]) -> 5 | AP18: =SUMIF(RawData[Customer_ID],AL18,RawData[Revenue]) -> 130620.25 | AQ18: =SUMIF(RawData[Customer_ID],AL18,RawData[Profit]) -> 13749.5 | AR18: =IF(AN18=0,0,AP18/AN18) -> 130620.25 | AS18: =IF(AN18=1,"One-time",IF(AN18<=4,"Occasional",IF(AN18<=8,"Loyal","Review"))) -> One-time | DQ18: Bookshelf | DR18: =SUMIFS(RawData[Revenue],RawData[Product_Name],DQ18, RawData[Order_Date],">="&DATE(2025,11,1),RawData[Order_Date],"<"&DATE(2025,12,1)) -> 193735.19 | DS18: =SUMIFS(RawData[Profit],RawData[Product_Name],DQ18, RawData[Order_Date],">="&DATE(2025,11,1),RawData[Order_Date],"<"&DATE(2025,12,1)) -> 29960.39 | DT18: =DS18/DR18 -> 0.15464609 | DU18: =SUMIFS(RawData[Revenue],RawData[Product_Name],DQ18, RawData[Order_Date],">="&DATE(2025,12,1),RawData[Order_Date],"<"&DATE(2026,1,1)) -> 174173.2 | DV18: =SUMIFS(RawData[Profit],RawData[Product_Name],DQ18, RawData[Order_Date],">="&DATE(2025,12,1),RawData[Order_Date],"<"&DATE(2026,1,1)) -> 28595.6 | DW18: =DV18/DU18 -> 0.1641791
AD19: Calculator | AE19: Office Supplies | AF19: =COUNTIF(RawData[Product_Name],AD19) -> 139 | AG19: =SUMIF(RawData[Product_Name],AD19,RawData[Quantity]) -> 411 | AH19: =SUMIF(RawData[Product_Name],AD19,RawData[Revenue]) -> 253799 | AI19: =SUMIF(RawData[Product_Name],AD19,RawData[Profit]) -> 61451 | AJ19: =AI19/AH19 -> 0.24212467 | AL19: C0017 | AM19: Prachi Solanki | AN19: =COUNTIF(RawData[Customer_ID],AL19) -> 2 | AO19: =SUMIF(RawData[Customer_ID],AL19,RawData[Quantity]) -> 8 | AP19: =SUMIF(RawData[Customer_ID],AL19,RawData[Revenue]) -> 189616.2 | AQ19: =SUMIF(RawData[Customer_ID],AL19,RawData[Profit]) -> 32551.32 | AR19: =IF(AN19=0,0,AP19/AN19) -> 94808.1 | AS19: =IF(AN19=1,"One-time",IF(AN19<=4,"Occasional",IF(AN19<=8,"Loyal","Review"))) -> Occasional
AD20: Notebook | AE20: Office Supplies | AF20: =COUNTIF(RawData[Product_Name],AD20) -> 148 | AG20: =SUMIF(RawData[Product_Name],AD20,RawData[Quantity]) -> 430 | AH20: =SUMIF(RawData[Product_Name],AD20,RawData[Revenue]) -> 32497.6 | AI20: =SUMIF(RawData[Product_Name],AD20,RawData[Profit]) -> 8417.6 | AJ20: =AI20/AH20 -> 0.2590222 | AL20: C0018 | AM20: Sahil Sinha | AN20: =COUNTIF(RawData[Customer_ID],AL20) -> 4 | AO20: =SUMIF(RawData[Customer_ID],AL20,RawData[Quantity]) -> 14 | AP20: =SUMIF(RawData[Customer_ID],AL20,RawData[Revenue]) -> 151428.44 | AQ20: =SUMIF(RawData[Customer_ID],AL20,RawData[Profit]) -> 24295.08 | AR20: =IF(AN20=0,0,AP20/AN20) -> 37857.11 | AS20: =IF(AN20=1,"One-time",IF(AN20<=4,"Occasional",IF(AN20<=8,"Loyal","Review"))) -> Occasional
AD21: Pen Set | AE21: Office Supplies | AF21: =COUNTIF(RawData[Product_Name],AD21) -> 134 | AG21: =SUMIF(RawData[Product_Name],AD21,RawData[Quantity]) -> 429 | AH21: =SUMIF(RawData[Product_Name],AD21,RawData[Revenue]) -> 60961.5 | AI21: =SUMIF(RawData[Product_Name],AD21,RawData[Profit]) -> 19134 | AJ21: =AI21/AH21 -> 0.31387023 | AL21: C0019 | AM21: Arjun Mehta | AN21: =COUNTIF(RawData[Customer_ID],AL21) -> 2 | AO21: =SUMIF(RawData[Customer_ID],AL21,RawData[Quantity]) -> 4 | AP21: =SUMIF(RawData[Customer_ID],AL21,RawData[Revenue]) -> 27171.08 | AQ21: =SUMIF(RawData[Customer_ID],AL21,RawData[Profit]) -> 4042.87 | AR21: =IF(AN21=0,0,AP21/AN21) -> 13585.54 | AS21: =IF(AN21=1,"One-time",IF(AN21<=4,"Occasional",IF(AN21<=8,"Loyal","Review"))) -> Occasional
AD22: Markers | AE22: Office Supplies | AF22: =COUNTIF(RawData[Product_Name],AD22) -> 136 | AG22: =SUMIF(RawData[Product_Name],AD22,RawData[Quantity]) -> 419 | AH22: =SUMIF(RawData[Product_Name],AD22,RawData[Revenue]) -> 98857.5 | AI22: =SUMIF(RawData[Product_Name],AD22,RawData[Profit]) -> 33912.5 | AJ22: =AI22/AH22 -> 0.34304428 | AL22: C0020 | AM22: Gaurav Choudhary | AN22: =COUNTIF(RawData[Customer_ID],AL22) -> 2 | AO22: =SUMIF(RawData[Customer_ID],AL22,RawData[Quantity]) -> 3 | AP22: =SUMIF(RawData[Customer_ID],AL22,RawData[Revenue]) -> 80163.16 | AQ22: =SUMIF(RawData[Customer_ID],AL22,RawData[Profit]) -> 12369.72 | AR22: =IF(AN22=0,0,AP22/AN22) -> 40081.58 | AS22: =IF(AN22=1,"One-time",IF(AN22<=4,"Occasional",IF(AN22<=8,"Loyal","Review"))) -> Occasional
AD23: File Folder | AE23: Office Supplies | AF23: =COUNTIF(RawData[Product_Name],AD23) -> 155 | AG23: =SUMIF(RawData[Product_Name],AD23,RawData[Quantity]) -> 457 | AH23: =SUMIF(RawData[Product_Name],AD23,RawData[Revenue]) -> 51963.6 | AI23: =SUMIF(RawData[Product_Name],AD23,RawData[Profit]) -> 14672.4 | AJ23: =AI23/AH23 -> 0.28235919 | AL23: C0021 | AM23: Monika Shetty | AN23: =COUNTIF(RawData[Customer_ID],AL23) -> 8 | AO23: =SUMIF(RawData[Customer_ID],AL23,RawData[Quantity]) -> 20 | AP23: =SUMIF(RawData[Customer_ID],AL23,RawData[Revenue]) -> 173727.31 | AQ23: =SUMIF(RawData[Customer_ID],AL23,RawData[Profit]) -> 25996.34 | AR23: =IF(AN23=0,0,AP23/AN23) -> 21715.914 | AS23: =IF(AN23=1,"One-time",IF(AN23<=4,"Occasional",IF(AN23<=8,"Loyal","Review"))) -> Loyal
AL24: C0022 | AM24: Heena Desai | AN24: =COUNTIF(RawData[Customer_ID],AL24) -> 6 | AO24: =SUMIF(RawData[Customer_ID],AL24,RawData[Quantity]) -> 16 | AP24: =SUMIF(RawData[Customer_ID],AL24,RawData[Revenue]) -> 353550.42 | AQ24: =SUMIF(RawData[Customer_ID],AL24,RawData[Profit]) -> 32709.65 | AR24: =IF(AN24=0,0,AP24/AN24) -> 58925.07 | AS24: =IF(AN24=1,"One-time",IF(AN24<=4,"Occasional",IF(AN24<=8,"Loyal","Review"))) -> Loyal
AL25: C0023 | AM25: Ayaan Shetty | AN25: =COUNTIF(RawData[Customer_ID],AL25) -> 2 | AO25: =SUMIF(RawData[Customer_ID],AL25,RawData[Quantity]) -> 5 | AP25: =SUMIF(RawData[Customer_ID],AL25,RawData[Revenue]) -> 175775.16 | AQ25: =SUMIF(RawData[Customer_ID],AL25,RawData[Profit]) -> 31899.12 | AR25: =IF(AN25=0,0,AP25/AN25) -> 87887.58 | AS25: =IF(AN25=1,"One-time",IF(AN25<=4,"Occasional",IF(AN25<=8,"Loyal","Review"))) -> Occasional
AL26: C0024 | AM26: Saurabh Sinha | AN26: =COUNTIF(RawData[Customer_ID],AL26) -> 4 | AO26: =SUMIF(RawData[Customer_ID],AL26,RawData[Quantity]) -> 11 | AP26: =SUMIF(RawData[Customer_ID],AL26,RawData[Revenue]) -> 125738.78 | AQ26: =SUMIF(RawData[Customer_ID],AL26,RawData[Profit]) -> 13750.3 | AR26: =IF(AN26=0,0,AP26/AN26) -> 31434.695 | AS26: =IF(AN26=1,"One-time",IF(AN26<=4,"Occasional",IF(AN26<=8,"Loyal","Review"))) -> Occasional
AL27: C0025 | AM27: Payal Gill | AN27: =COUNTIF(RawData[Customer_ID],AL27) -> 3 | AO27: =SUMIF(RawData[Customer_ID],AL27,RawData[Quantity]) -> 9 | AP27: =SUMIF(RawData[Customer_ID],AL27,RawData[Revenue]) -> 72503.46 | AQ27: =SUMIF(RawData[Customer_ID],AL27,RawData[Profit]) -> 17091.86 | AR27: =IF(AN27=0,0,AP27/AN27) -> 24167.82 | AS27: =IF(AN27=1,"One-time",IF(AN27<=4,"Occasional",IF(AN27<=8,"Loyal","Review"))) -> Occasional
AL28: C0026 | AM28: Shivam Joshi | AN28: =COUNTIF(RawData[Customer_ID],AL28) -> 2 | AO28: =SUMIF(RawData[Customer_ID],AL28,RawData[Quantity]) -> 5 | AP28: =SUMIF(RawData[Customer_ID],AL28,RawData[Revenue]) -> 1182.5 | AQ28: =SUMIF(RawData[Customer_ID],AL28,RawData[Profit]) -> 407.5 | AR28: =IF(AN28=0,0,AP28/AN28) -> 591.25 | AS28: =IF(AN28=1,"One-time",IF(AN28<=4,"Occasional",IF(AN28<=8,"Loyal","Review"))) -> Occasional
AL29: C0027 | AM29: Rishi Reddy | AN29: =COUNTIF(RawData[Customer_ID],AL29) -> 1 | AO29: =SUMIF(RawData[Customer_ID],AL29,RawData[Quantity]) -> 5 | AP29: =SUMIF(RawData[Customer_ID],AL29,RawData[Revenue]) -> 5115 | AQ29: =SUMIF(RawData[Customer_ID],AL29,RawData[Profit]) -> 1540 | AR29: =IF(AN29=0,0,AP29/AN29) -> 5115 | AS29: =IF(AN29=1,"One-time",IF(AN29<=4,"Occasional",IF(AN29<=8,"Loyal","Review"))) -> One-time
AL30: C0028 | AM30: Vivek Shetty | AN30: =COUNTIF(RawData[Customer_ID],AL30) -> 4 | AO30: =SUMIF(RawData[Customer_ID],AL30,RawData[Quantity]) -> 15 | AP30: =SUMIF(RawData[Customer_ID],AL30,RawData[Revenue]) -> 86425.25 | AQ30: =SUMIF(RawData[Customer_ID],AL30,RawData[Profit]) -> 16208 | AR30: =IF(AN30=0,0,AP30/AN30) -> 21606.312 | AS30: =IF(AN30=1,"One-time",IF(AN30<=4,"Occasional",IF(AN30<=8,"Loyal","Review"))) -> Occasional
AL31: C0029 | AM31: Rohan Trivedi | AN31: =COUNTIF(RawData[Customer_ID],AL31) -> 4 | AO31: =SUMIF(RawData[Customer_ID],AL31,RawData[Quantity]) -> 11 | AP31: =SUMIF(RawData[Customer_ID],AL31,RawData[Revenue]) -> 59627.88 | AQ31: =SUMIF(RawData[Customer_ID],AL31,RawData[Profit]) -> 11137.92 | AR31: =IF(AN31=0,0,AP31/AN31) -> 14906.97 | AS31: =IF(AN31=1,"One-time",IF(AN31<=4,"Occasional",IF(AN31<=8,"Loyal","Review"))) -> Occasional
AL32: C0030 | AM32: Sneha Arora | AN32: =COUNTIF(RawData[Customer_ID],AL32) -> 0 | AO32: =SUMIF(RawData[Customer_ID],AL32,RawData[Quantity]) -> 0 | AP32: =SUMIF(RawData[Customer_ID],AL32,RawData[Revenue]) -> 0 | AQ32: =SUMIF(RawData[Customer_ID],AL32,RawData[Profit]) -> 0 | AR32: =IF(AN32=0,0,AP32/AN32) -> 0 | AS32: =IF(AN32=1,"One-time",IF(AN32<=4,"Occasional",IF(AN32<=8,"Loyal","Review"))) -> Occasional
AL33: C0031 | AM33: Siddharth Saxena | AN33: =COUNTIF(RawData[Customer_ID],AL33) -> 2 | AO33: =SUMIF(RawData[Customer_ID],AL33,RawData[Quantity]) -> 4 | AP33: =SUMIF(RawData[Customer_ID],AL33,RawData[Revenue]) -> 102474 | AQ33: =SUMIF(RawData[Customer_ID],AL33,RawData[Profit]) -> 15564 | AR33: =IF(AN33=0,0,AP33/AN33) -> 51237 | AS33: =IF(AN33=1,"One-time",IF(AN33<=4,"Occasional",IF(AN33<=8,"Loyal","Review"))) -> Occasional
AL34: C0032 | AM34: Saurabh Malhotra | AN34: =COUNTIF(RawData[Customer_ID],AL34) -> 4 | AO34: =SUMIF(RawData[Customer_ID],AL34,RawData[Quantity]) -> 14 | AP34: =SUMIF(RawData[Customer_ID],AL34,RawData[Revenue]) -> 176057.54 | AQ34: =SUMIF(RawData[Customer_ID],AL34,RawData[Profit]) -> 27900.3 | AR34: =IF(AN34=0,0,AP34/AN34) -> 44014.385 | AS34: =IF(AN34=1,"One-time",IF(AN34<=4,"Occasional",IF(AN34<=8,"Loyal","Review"))) -> Occasional
AL35: C0033 | AM35: Mayank Sinha | AN35: =COUNTIF(RawData[Customer_ID],AL35) -> 3 | AO35: =SUMIF(RawData[Customer_ID],AL35,RawData[Quantity]) -> 9 | AP35: =SUMIF(RawData[Customer_ID],AL35,RawData[Revenue]) -> 939.6 | AQ35: =SUMIF(RawData[Customer_ID],AL35,RawData[Profit]) -> 282 | AR35: =IF(AN35=0,0,AP35/AN35) -> 313.2 | AS35: =IF(AN35=1,"One-time",IF(AN35<=4,"Occasional",IF(AN35<=8,"Loyal","Review"))) -> Occasional
... AL902: C0900 | AM902: Swati Tripathi | AN902: =COUNTIF(RawData[Customer_ID],AL902) -> 1 | AO902: =SUMIF(RawData[Customer_ID],AL902,RawData[Quantity]) -> 4 | AP902: =SUMIF(RawData[Customer_ID],AL902,RawData[Revenue]) -> 202396.32 | AQ902: =SUMIF(RawData[Customer_ID],AL902,RawData[Profit]) -> 21999.6 | AR902: =IF(AN902=0,0,AP902/AN902) -> 202396.32 | AS902: =IF(AN902=1,"One-time",IF(AN902<=4,"Occasional",IF(AN902<=8,"Loyal","Review"))) -> One-time

Sheet Master_data
A1: City | B1: Region | E1: Product_ID | F1: Category | G1: Product | J1: Salesperson_ID | K1: Salesperson_Name | N1: Payment_Mode | P1: Sales_Channel
A2: Mumbai | B2: West | E2: P001 | F2: Electronics | G2: Laptop | J2: SP001 | K2: Rahul Sharma | N2: UPI | P2: Online
A3: Pune | B3: West | E3: P002 | F3: Electronics | G3: Smartphone | J3: SP002 | K3: Priya Patel | N3: Credit Card | P3: Offline
A4: Ahmedabad | B4: West | E4: P003 | F4: Electronics | G4: Tablet | J4: SP003 | K4: Aman Verma | N4: Debit Card
A5: Surat | B5: West | E5: P004 | F5: Electronics | G5: Smartwatch | J5: SP004 | K5: Neha Gupta | N5: Cash
A6: Delhi | B6: North | E6: P005 | F6: Electronics | G6: Wireless Earbuds | J6: SP005 | K6: Arjun Mehta | N6: Net Banking
A7: Jaipur | B7: North | E7: P006 | F7: Electronics | G7: Bluetooth Speaker | J7: SP006 | K7: Sneha Iyer
A8: Lucknow | B8: North | E8: P007 | F8: Electronics | G8: Monitor | J8: SP007 | K8: Karan Singh
A9: Kolkata | B9: East | E9: P008 | F9: Electronics | G9: Keyboard | J9: SP008 | K9: Pooja Nair
A10: Bhubaneswar | B10: East | E10: P009 | F10: Electronics | G10: Mouse | J10: SP009 | K10: Vivek Joshi
A11: Chennai | B11: South | E11: P010 | F11: Electronics | G11: Printer | J11: SP010 | K11: Anjali Desai
A12: Bengaluru | B12: South | E12: P011 | F12: Furniture | G12: Office Chair
A13: Hyderabad | B13: South | E13: P012 | F13: Furniture | G13: Study Desk
E14: P013 | F14: Furniture | G14: Bookshelf | J14: Key | K14: Min_Discount | L14: Max_Discount
A15: Month | B15: Season | E15: P014 | F15: Furniture | G15: Coffee Table | J15: Regular-Electronics | K15: 3 | L15: 8
A16: 1 | B16: Back to School | E16: P015 | F16: Furniture | G16: Sofa | J16: Regular-Furniture | K16: 5 | L16: 10
A17: 2 | B17: Regular | E17: P016 | F17: Furniture | G17: Dining Table | J17: Regular-Office Supplies | K17: 0 | L17: 5
A18: 3 | B18: Regular | E18: P017 | F18: Furniture | G18: Wardrobe | J18: Festival-Electronics | K18: 10 | L18: 18
A19: 4 | B19: Regular | E19: P018 | F19: Furniture | G19: TV Unit | J19: Festival-Furniture | K19: 12 | L19: 20
A20: 5 | B20: Back to School | E20: P019 | F20: Furniture | G20: Bed Frame | J20: Festival-Office Supplies | K20: 3 | L20: 8
A21: 6 | B21: Back to School | E21: P020 | F21: Furniture | G21: Shoe Rack | J21: Back to School-Electronics | K21: 5 | L21: 10
A22: 7 | B22: Regular | E22: P021 | F22: Office Supplies | G22: Notebook | J22: Back to School-Furniture | K22: 2 | L22: 5
A23: 8 | B23: Regular | E23: P022 | F23: Office Supplies | G23: Pen Set | J23: Back to School-Office Supplies | K23: 8 | L23: 15
A24: 9 | B24: Regular | E24: P023 | F24: Office Supplies | G24: Marker Pack
A25: 10 | B25: Regular | E25: P024 | F25: Office Supplies | G25: Stapler
A26: 11 | B26: Festival | E26: P025 | F26: Office Supplies | G26: File Folder
A27: 12 | B27: Festival | E27: P026 | F27: Office Supplies | G27: Desk Organizer
E28: P027 | F28: Office Supplies | G28: Calculator
E29: P028 | F29: Office Supplies | G29: Sticky Notes
E30: P029 | F30: Office Supplies | G30: Paper Ream
E31: P030 | F31: Office Supplies | G31: Whiteboard

Sheet Raw_data
A1: Order_ID | B1: Order_Date | C1: Customer_ID | D1: Customer_Name | E1: Gender | F1: Age | G1: City | H1: Region | I1: Product_ID | J1: Product_Name | K1: Product_Category | L1: Quantity | M1: Unit_Price | N1: Cost_Price | O1: Discount% | P1: Revenue | Q1: Total_Cost | R1: Profit | S1: Sales_Channel | T1: Payment_Mode | U1: Salesperson_ID
A2: ORD00001 | B2: 45976 | C2: C0832 | D2: Ishita Solanki | E2: Female | F2: 38 | G2: Hyderabad | H2: South | I2: P018 | J2: Pen Set | K2: Office Supplies | L2: 3 | M2: 150 | N2: 97.5 | O2: 3 | P2: 436.5 | Q2: 292.5 | R2: 144 | S2: Online | T2: Credit Card | U2: S008
A3: ORD00002 | B3: 45672 | C3: C0605 | D3: Priya Pillai | E3: Female | F3: 34 | G3: Kolkata | H3: East | I3: P005 | J3: Printer | K3: Electronics | L3: 3 | M3: 13749 | N3: 10999.2 | O3: 9 | P3: 37534.77 | Q3: 32997.6 | R3: 4537.17 | S3: In-Store | T3: Cash | U3: S009
A4: ORD00003 | B4: 45984 | C4: C0447 | D4: Rohit Malhotra | E4: Male | F4: 58 | G4: Mumbai | H4: West | I4: P010 | J4: Mouse | K4: Electronics | L4: 3 | M4: 1100 | N4: 715 | O4: 12 | P4: 2904 | Q4: 2145 | R4: 759 | S4: Online | T4: Debit Card | U4: S006
A5: ORD00004 | B5: 46017 | C5: C0013 | D5: Adarsh Malhotra | E5: Male | F5: 32 | G5: Jaipur | H5: North | I5: P014 | J5: Wardrobe | K5: Furniture | L5: 1 | M5: 31999 | N5: 25599.2 | O5: 15 | P5: 27199.15 | Q5: 25599.2 | R5: 1599.95 | S5: In-Store | T5: Debit Card | U5: S009
A6: ORD00005 | B6: 45890 | C6: C0336 | D6: Varun Solanki | E6: Male | F6: 34 | G6: Jaipur | H6: North | I6: P001 | J6: Laptop | K6: Electronics | L6: 4 | M6: 54999 | N6: 45099.18 | O6: 6 | P6: 206796.24 | Q6: 180396.72 | R6: 26399.52 | S6: In-Store | T6: Credit Card | U6: S008
A7: ORD00006 | B7: 45813 | C7: C0684 | D7: Pooja Jain | E7: Female | F7: 22 | G7: Pune | H7: West | I7: P007 | J7: External Hard Drive | K7: Electronics | L7: 5 | M7: 6900 | N7: 5727 | O7: 6 | P7: 32430 | Q7: 28635 | R7: 3795 | S7: In-Store | T7: Debit Card | U7: S007
A8: ORD00007 | B8: 45948 | C8: C0728 | D8: Pranav Desai | E8: Male | F8: 19 | G8: Hyderabad | H8: South | I8: P007 | J8: External Hard Drive | K8: Electronics | L8: 3 | M8: 6900 | N8: 5727 | O8: 4 | P8: 19872 | Q8: 17181 | R8: 2691 | S8: In-Store | T8: Credit Card | U8: S002
A9: ORD00008 | B9: 45780 | C9: C0766 | D9: Ritika Iyer | E9: Female | F9: 21 | G9: Indore | H9: West | I9: P013 | J9: Sofa | K9: Furniture | L9: 2 | M9: 42999 | N9: 33539.22 | O9: 5 | P9: 81698.1 | Q9: 67078.44 | R9: 14619.66 | S9: In-Store | T9: Debit Card | U9: S004
A10: ORD00009 | B10: 45808 | C10: C0660 | D10: Yash Sharma | E10: Male | F10: 61 | G10: Jaipur | H10: North | I10: P002 | J10: Smartphone | K10: Electronics | L10: 1 | M10: 35800 | N10: 28640 | O10: 7 | P10: 33294 | Q10: 28640 | R10: 4654 | S10: In-Store | T10: Credit Card | U10: S005
A11: ORD00010 | B11: 45823 | C11: C0620 | D11: Rohit Banerjee | E11: Male | F11: 51 | G11: Indore | H11: West | I11: P002 | J11: Smartphone | K11: Electronics | L11: 3 | M11: 35800 | N11: 28640 | O11: 7 | P11: 99882 | Q11: 85920 | R11: 13962 | S11: Online | T11: Debit Card | U11: S007
A12: ORD00011 | B12: 45935 | C12: C0018 | D12: Sahil Sinha | E12: Male | F12: 21 | G12: Hyderabad | H12: South | I12: P005 | J12: Printer | K12: Electronics | L12: 5 | M12: 13749 | N12: 10999.2 | O12: 4 | P12: 65995.2 | Q12: 54996 | R12: 10999.2 | S12: In-Store | T12: Credit Card | U12: S009
A13: ORD00012 | B13: 45730 | C13: C0288 | D13: Khushi Rao | E13: Female | F13: 52 | G13: Bengaluru | H13: South | I13: P003 | J13: Tablet | K13: Electronics | L13: 4 | M13: 27499 | N13: 23374.15 | O13: 5 | P13: 104496.2 | Q13: 93496.6 | R13: 10999.6 | S13: In-Store | T13: UPI | U13: S007
... A3001: ORD03000 | B3001: 45866 | C3001: C0239 | D3001: Neha Jain | E3001: Female | F3001: 60 | G3001: Delhi | H3001: North | I3001: P003 | J3001: Tablet | K3001: Electronics | L3001: 2 | M3001: 27499 | N3001: 23374.15 | O3001: 5 | P3001: 52248.1 | Q3001: 46748.3 | R3001: 5499.8 | S3001: In-Store | T3001: UPI | U3001: S009

Sheet Orders_Helper
A1: Order_Type | B1: Percentage | C1: Products_per_Order | D1: Approx_Orders | F1: Month | G1: Weight | H1: Orders | J1: Segment | K1: Percentage | L1: Customers | N1: Day | O1: Weight
A2: Single | B2: 0.6 | C2: 1 | D2: 1140 | F2: Jan | G2: 0.11 | H2: 209 | J2: One-time | K2: 0.35 | L2: 315 | N2: Monday | O2: 0.08
A3: Bundle | B3: 0.3 | C3: 2 | D3: 570 | F3: Feb | G3: 0.06 | H3: 114 | J3: Occasional | K3: 0.45 | L3: 405 | N3: Tuesday | O3: 0.1
A4: Mixed | B4: 0.1 | C4: 3 | D4: 190 | F4: Mar | G4: 0.08 | H4: 152 | J4: Loyal | K4: 0.2 | L4: 180 | N4: Wednesday | O4: 0.13
F5: Apr | G5: 0.06 | H5: 114 | N5: Thursday | O5: 0.14
F6: May | G6: 0.09 | H6: 171 | N6: Friday | O6: 0.17
F7: Jun | G7: 0.11 | H7: 209 | N7: Saturday | O7: 0.19
F8: Jul | G8: 0.07 | H8: 133 | N8: Sunday | O8: 0.19
F9: Aug | G9: 0.07 | H9: 133
F10: Sep | G10: 0.08 | H10: 152
F11: Oct | G11: 0.09 | H11: 171
F12: Nov | G12: 0.11 | H12: 209

Sheet Customer_Helper
A1: First_Name | B1: Gender | D1: Last_Name | F1: City | G1: Region | H1: Customers | J1: Customer_Type | K1: Customers | M1: Gender | N1: Customers | P1: Age_Group | Q1: Min | R1: Max | S1: Customers
A2: Aarav | B2: Male | D2: Patel | F2: Mumbai | G2: West | H2: 140 | J2: One-time | K2: 315 | M2: Male | N2: 495 | P2: 18–24 | Q2: 18 | R2: 24 | S2: 225
A3: Vivaan | B3: Male | D3: Shah | F3: Pune | G3: West | H3: 100 | J3: Occasional | K3: 405 | M3: Female | N3: 405 | P3: 25–34 | Q3: 25 | R3: 34 | S3: 315
A4: Aditya | B4: Male | D4: Sharma | F4: Ahmedabad | G4: West | H4: 70 | J4: Loyal | K4: 180 | P4: 35–44 | Q4: 35 | R4: 44 | S4: 198
A5: Arjun | B5: Male | D5: Singh | F5: Indore | G5: West | H5: 40 | P5: 45–54 | Q5: 45 | R5: 54 | S5: 108
A6: Rohan | B6: Male | D6: Mehta | F6: Nagpur | G6: West | H6: 40 | P6: 55–65 | Q6: 55 | R6: 65 | S6: 54
A7: Rahul | B7: Male | D7: Gupta | F7: Delhi | G7: North | H7: 95
A8: Akash | B8: Male | D8: Verma | F8: Jaipur | G8: North | H8: 55
A9: Siddharth | B9: Male | D9: Joshi | F9: Lucknow | G9: North | H9: 50
A10: Dhruv | B10: Male | D10: Desai | F10: Bengaluru | G10: South | H10: 90
A11: Yash | B11: Male | D11: Nair | F11: Hyderabad | G11: South | H11: 80
A12: Manav | B12: Male | D12: Iyer | F12: Chennai | G12: South | H12: 75
A13: Aryan | B13: Male | D13: Kulkarni | F13: Kolkata | G13: East | H13: 65
A14: Kabir | B14: Male | D14: Mishra
A15: Krish | B15: Male | D15: Choudhary
A16: Harsh | B16: Male | D16: Yadav
A17: Nikhil | B17: Male | D17: Jain
A18: Varun | B18: Male | D18: Kapoor
A19: Aniket | B19: Male | D19: Bhat
A20: Tanmay | B20: Male | D20: Das
A21: Kunal | B21: Male | D21: Reddy
A22: Ayaan | B22: Male | D22: Rao
A23: Ishaan | B23: Male | D23: Ghosh
A24: Atharv | B24: Male | D24: Banerjee
A25: Dev | B25: Male | D25: Sinha
... A51: Sahil | B51: Male | D51: Arora
A52: Priya | B52: Female
A53: Ananya | B53: Female
A54: Aditi | B54: Female
A55: Sneha | B55: Female
A56: Kavya | B56: Female
A57: Diya | B57: Female
A58: Meera | B58: Female
A59: Riya | B59: Female
A60: Pooja | B60: Female
A61: Neha | B61: Female
A62: Simran | B62: Female
A63: Nisha | B63: Female
... A101: Niyati | B101: Female

Sheet Salesperson_Helper
A1: Salesperson_ID | B1: Salesperson_Name | C1: Gender | E1: Salesperson_ID | F1: Team | H1: Salesperson_ID | I1: City | K1: City | L1: Region
A2: S001 | B2: Aarav Patel | C2: Male | E2: S001 | F2: Alpha | H2: S001 | I2: Mumbai | K2: Mumbai | L2: West
A3: S002 | B3: Priya Shah | C3: Female | E3: S002 | F3: Alpha | H3: S002 | I3: Pune | K3: Pune | L3: West
A4: S003 | B4: Rahul Sharma | C4: Male | E4: S003 | F4: Beta | H4: S003 | I4: Delhi | K4: Ahmedabad | L4: West
A5: S004 | B5: Sneha Mehta | C5: Female | E5: S004 | F5: Beta | H5: S004 | I5: Jaipur | K5: Indore | L5: West
A6: S005 | B6: Vivek Gupta | C6: Male | E6: S005 | F6: Gamma | H6: S005 | I6: Bengaluru | K6: Nagpur | L6: West
A7: S006 | B7: Ananya Joshi | C7: Female | E7: S006 | F7: Gamma | H7: S006 | I7: Hyderabad | K7: Delhi | L7: North
A8: S007 | B8: Rohit Desai | C8: Male | E8: S007 | F8: Delta | H8: S007 | I8: Chennai | K8: Jaipur | L8: North
A9: S008 | B9: Kavya Iyer | C9: Female | E9: S008 | F9: Delta | H9: S008 | I9: Kolkata | K9: Lucknow | L9: North
A10: S009 | B10: Aditya Singh | C10: Male | E10: S009 | F10: Omega | H10: S009 | I10: Ahmedabad | K10: Bengaluru | L10: South
A11: S010 | B11: Neha Verma | C11: Female | E11: S010 | F11: Omega | H11: S010 | I11: Nagpur | K11: Hyderabad | L11: South
K12: Chennai | L12: South
K13: Kolkata | L13: East

Sheet Salesperson_Masterdata
A1: Salesperson_ID | B1: Salesperson_Name | C1: Gender | D1: Team | E1: City | F1: Region
A2: S001 | B2: =VLOOKUP(A2,Salesperson_Helper!$A$2:$C$11,2,FALSE) -> Aarav Patel | C2: =VLOOKUP(A2,Salesperson_Helper!$A$2:$C$11,3,FALSE) -> Male | D2: =VLOOKUP(A2,Salesperson_Helper!$E$2:$F$11,2,FALSE) -> Alpha | E2: =VLOOKUP(A2,Salesperson_Helper!$H$2:$I$11,2,FALSE) -> Mumbai | F2: =VLOOKUP(E2,Salesperson_Helper!$K$2:$L$13,2,FALSE) -> West
A3: S002 | B3: =VLOOKUP(A3,Salesperson_Helper!$A$2:$C$11,2,FALSE) -> Priya Shah | C3: =VLOOKUP(A3,Salesperson_Helper!$A$2:$C$11,3,FALSE) -> Female | D3: =VLOOKUP(A3,Salesperson_Helper!$E$2:$F$11,2,FALSE) -> Alpha | E3: =VLOOKUP(A3,Salesperson_Helper!$H$2:$I$11,2,FALSE) -> Pune | F3: =VLOOKUP(E3,Salesperson_Helper!$K$2:$L$13,2,FALSE) -> West
A4: S003 | B4: =VLOOKUP(A4,Salesperson_Helper!$A$2:$C$11,2,FALSE) -> Rahul Sharma | C4: =VLOOKUP(A4,Salesperson_Helper!$A$2:$C$11,3,FALSE) -> Male | D4: =VLOOKUP(A4,Salesperson_Helper!$E$2:$F$11,2,FALSE) -> Beta | E4: =VLOOKUP(A4,Salesperson_Helper!$H$2:$I$11,2,FALSE) -> Delhi | F4: =VLOOKUP(E4,Salesperson_Helper!$K$2:$L$13,2,FALSE) -> North
A5: S004 | B5: =VLOOKUP(A5,Salesperson_Helper!$A$2:$C$11,2,FALSE) -> Sneha Mehta | C5: =VLOOKUP(A5,Salesperson_Helper!$A$2:$C$11,3,FALSE) -> Female | D5: =VLOOKUP(A5,Salesperson_Helper!$E$2:$F$11,2,FALSE) -> Beta | E5: =VLOOKUP(A5,Salesperson_Helper!$H$2:$I$11,2,FALSE) -> Jaipur | F5: =VLOOKUP(E5,Salesperson_Helper!$K$2:$L$13,2,FALSE) -> North
A6: S005 | B6: =VLOOKUP(A6,Salesperson_Helper!$A$2:$C$11,2,FALSE) -> Vivek Gupta | C6: =VLOOKUP(A6,Salesperson_Helper!$A$2:$C$11,3,FALSE) -> Male | D6: =VLOOKUP(A6,Salesperson_Helper!$E$2:$F$11,2,FALSE) -> Gamma | E6: =VLOOKUP(A6,Salesperson_Helper!$H$2:$I$11,2,FALSE) -> Bengaluru | F6: =VLOOKUP(E6,Salesperson_Helper!$K$2:$L$13,2,FALSE) -> South
A7: S006 | B7: =VLOOKUP(A7,Salesperson_Helper!$A$2:$C$11,2,FALSE) -> Ananya Joshi | C7: =VLOOKUP(A7,Salesperson_Helper!$A$2:$C$11,3,FALSE) -> Female | D7: =VLOOKUP(A7,Salesperson_Helper!$E$2:$F$11,2,FALSE) -> Gamma | E7: =VLOOKUP(A7,Salesperson_Helper!$H$2:$I$11,2,FALSE) -> Hyderabad | F7: =VLOOKUP(E7,Salesperson_Helper!$K$2:$L$13,2,FALSE) -> South
A8: S007 | B8: =VLOOKUP(A8,Salesperson_Helper!$A$2:$C$11,2,FALSE) -> Rohit Desai | C8: =VLOOKUP(A8,Salesperson_Helper!$A$2:$C$11,3,FALSE) -> Male | D8: =VLOOKUP(A8,Salesperson_Helper!$E$2:$F$11,2,FALSE) -> Delta | E8: =VLOOKUP(A8,Salesperson_Helper!$H$2:$I$11,2,FALSE) -> Chennai | F8: =VLOOKUP(E8,Salesperson_Helper!$K$2:$L$13,2,FALSE) -> South
A9: S008 | B9: =VLOOKUP(A9,Salesperson_Helper!$A$2:$C$11,2,FALSE) -> Kavya Iyer | C9: =VLOOKUP(A9,Salesperson_Helper!$A$2:$C$11,3,FALSE) -> Female | D9: =VLOOKUP(A9,Salesperson_Helper!$E$2:$F$11,2,FALSE) -> Delta | E9: =VLOOKUP(A9,Salesperson_Helper!$H$2:$I$11,2,FALSE) -> Kolkata | F9: =VLOOKUP(E9,Salesperson_Helper!$K$2:$L$13,2,FALSE) -> East
A10: S009 | B10: =VLOOKUP(A10,Salesperson_Helper!$A$2:$C$11,2,FALSE) -> Aditya Singh | C10: =VLOOKUP(A10,Salesperson_Helper!$A$2:$C$11,3,FALSE) -> Male | D10: =VLOOKUP(A10,Salesperson_Helper!$E$2:$F$11,2,FALSE) -> Omega | E10: =VLOOKUP(A10,Salesperson_Helper!$H$2:$I$11,2,FALSE) -> Ahmedabad | F10: =VLOOKUP(E10,Salesperson_Helper!$K$2:$L$13,2,FALSE) -> West
A11: S010 | B11: =VLOOKUP(A11,Salesperson_Helper!$A$2:$C$11,2,FALSE) -> Neha Verma | C11: =VLOOKUP(A11,Salesperson_Helper!$A$2:$C$11,3,FALSE) -> Female | D11: =VLOOKUP(A11,Salesperson_Helper!$E$2:$F$11,2,FALSE) -> Omega | E11: =VLOOKUP(A11,Salesperson_Helper!$H$2:$I$11,2,FALSE) -> Nagpur | F11: =VLOOKUP(E11,Salesperson_Helper!$K$2:$L$13,2,FALSE) -> West

Sheet Customer_Masterdata
A1: Customer_ID | B1: Customer_Name | C1: Gender | D1: Age | E1: City | F1: Region | G1: Customer_Type
A2: ="C"&TEXT(ROW()-1,"0000") -> C0001 | B2: Prachi Choudhary | C2: =VLOOKUP(LEFT(B2,FIND(" ",B2)-1),Customer_Helper!$A$2:$B$101,2,FALSE) -> Female | D2: 52 | E2: Hyderabad | F2: =VLOOKUP(E2,Customer_Helper!$F$2:$G$13,2,FALSE) -> South | G2: One-time
A3: ="C"&TEXT(ROW()-1,"0000") -> C0002 | B3: Palak Pawar | C3: =VLOOKUP(LEFT(B3,FIND(" ",B3)-1),Customer_Helper!$A$2:$B$101,2,FALSE) -> Female | D3: 23 | E3: Mumbai | F3: =VLOOKUP(E3,Customer_Helper!$F$2:$G$13,2,FALSE) -> West | G3: Occasional
A4: ="C"&TEXT(ROW()-1,"0000") -> C0003 | B4: Anjali Bose | C4: =VLOOKUP(LEFT(B4,FIND(" ",B4)-1),Customer_Helper!$A$2:$B$101,2,FALSE) -> Female | D4: 33 | E4: Ahmedabad | F4: =VLOOKUP(E4,Customer_Helper!$F$2:$G$13,2,FALSE) -> West | G4: One-time
A5: ="C"&TEXT(ROW()-1,"0000") -> C0004 | B5: Akash Kapoor | C5: =VLOOKUP(LEFT(B5,FIND(" ",B5)-1),Customer_Helper!$A$2:$B$101,2,FALSE) -> Male | D5: 61 | E5: Mumbai | F5: =VLOOKUP(E5,Customer_Helper!$F$2:$G$13,2,FALSE) -> West | G5: Loyal
A6: ="C"&TEXT(ROW()-1,"0000") -> C0005 | B6: Bhavya Kapoor | C6: =VLOOKUP(LEFT(B6,FIND(" ",B6)-1),Customer_Helper!$A$2:$B$101,2,FALSE) -> Female | D6: 49 | E6: Pune | F6: =VLOOKUP(E6,Customer_Helper!$F$2:$G$13,2,FALSE) -> West | G6: Loyal
A7: ="C"&TEXT(ROW()-1,"0000") -> C0006 | B7: Rudra Gupta | C7: =VLOOKUP(LEFT(B7,FIND(" ",B7)-1),Customer_Helper!$A$2:$B$101,2,FALSE) -> Male | D7: 23 | E7: Pune | F7: =VLOOKUP(E7,Customer_Helper!$F$2:$G$13,2,FALSE) -> West | G7: Loyal
A8: ="C"&TEXT(ROW()-1,"0000") -> C0007 | B8: Diya Choudhary | C8: =VLOOKUP(LEFT(B8,FIND(" ",B8)-1),Customer_Helper!$A$2:$B$101,2,FALSE) -> Female | D8: 23 | E8: Delhi | F8: =VLOOKUP(E8,Customer_Helper!$F$2:$G$13,2,FALSE) -> North | G8: Occasional
A9: ="C"&TEXT(ROW()-1,"0000") -> C0008 | B9: Adarsh Verma | C9: =VLOOKUP(LEFT(B9,FIND(" ",B9)-1),Customer_Helper!$A$2:$B$101,2,FALSE) -> Male | D9: 40 | E9: Bengaluru | F9: =VLOOKUP(E9,Customer_Helper!$F$2:$G$13,2,FALSE) -> South | G9: One-time
A10: ="C"&TEXT(ROW()-1,"0000") -> C0009 | B10: Krish Gupta | C10: =VLOOKUP(LEFT(B10,FIND(" ",B10)-1),Customer_Helper!$A$2:$B$101,2,FALSE) -> Male | D10: 24 | E10: Jaipur | F10: =VLOOKUP(E10,Customer_Helper!$F$2:$G$13,2,FALSE) -> North | G10: Occasional
A11: ="C"&TEXT(ROW()-1,"0000") -> C0010 | B11: Isha Singh | C11: =VLOOKUP(LEFT(B11,FIND(" ",B11)-1),Customer_Helper!$A$2:$B$101,2,FALSE) -> Female | D11: 39 | E11: Nagpur | F11: =VLOOKUP(E11,Customer_Helper!$F$2:$G$13,2,FALSE) -> West | G11: Occasional
A12: ="C"&TEXT(ROW()-1,"0000") -> C0011 | B12: Swati Jain | C12: =VLOOKUP(LEFT(B12,FIND(" ",B12)-1),Customer_Helper!$A$2:$B$101,2,FALSE) -> Female | D12: 50 | E12: Nagpur | F12: =VLOOKUP(E12,Customer_Helper!$F$2:$G$13,2,FALSE) -> West | G12: One-time
A13: ="C"&TEXT(ROW()-1,"0000") -> C0012 | B13: Trisha Jain | C13: =VLOOKUP(LEFT(B13,FIND(" ",B13)-1),Customer_Helper!$A$2:$B$101,2,FALSE) -> Female | D13: 28 | E13: Indore | F13: =VLOOKUP(E13,Customer_Helper!$F$2:$G$13,2,FALSE) -> West | G13: Loyal
... A901: ="C"&TEXT(ROW()-1,"0000") -> C0900 | B901: Swati Tripathi | C901: =VLOOKUP(LEFT(B901,FIND(" ",B901)-1),Customer_Helper!$A$2:$B$101,2,FALSE) -> Female | D901: 60 | E901: Indore | F901: =VLOOKUP(E901,Customer_Helper!$F$2:$G$13,2,FALSE) -> West | G901: Occasional

Sheet Product_Masterdata
A1: Product_ID | B1: Category | C1: Product_Name | D1: Product_Role | E1: Bundle_Group | F1: Unit_Price (₹) | G1: Profit_Margin (%) | H1: Cost_Price (₹) | I1: Demand_Level | J1: Seasonal_Boost | K1: Min_Order_Qty | L1: Max_Order_Qty
A2: P001 | B2: Electronics | C2: Laptop | D2: Hero Product | E2: Tech Essentials | F2: 54999 | G2: 18 | H2: =Table10[[#This Row],[Unit_Price (₹)]]*(1-Table10[[#This Row],[Profit_Margin (%)]]/100) -> 45099.18 | I2: Low | J2: High | K2: 2 | L2: 10
A3: P002 | B3: Electronics | C3: Smartphone | D3: Premium Product | E3: Tech Essentials | F3: 35800 | G3: 20 | H3: =Table10[[#This Row],[Unit_Price (₹)]]*(1-Table10[[#This Row],[Profit_Margin (%)]]/100) -> 28640 | I3: Medium | J3: High | K3: 1 | L3: 5
A4: P003 | B4: Electronics | C4: Tablet | D4: Premium Product | E4: Tech Essentials | F4: 27499 | G4: 15 | H4: =Table10[[#This Row],[Unit_Price (₹)]]*(1-Table10[[#This Row],[Profit_Margin (%)]]/100) -> 23374.15 | I4: Low | J4: Medium | K4: 1 | L4: 2
A5: P004 | B5: Electronics | C5: Monitor | D5: Workspace Essential | E5: Workspace Setup | F5: 16499 | G5: 12 | H5: =Table10[[#This Row],[Unit_Price (₹)]]*(1-Table10[[#This Row],[Profit_Margin (%)]]/100) -> 14519.12 | I5: Medium | J5: Medium | K5: 1 | L5: 3
A6: P005 | B6: Electronics | C6: Printer | D6: Office Essential | E6: Workspace Setup | F6: 13749 | G6: 20 | H6: =Table10[[#This Row],[Unit_Price (₹)]]*(1-Table10[[#This Row],[Profit_Margin (%)]]/100) -> 10999.2 | I6: Low | J6: Medium | K6: 1 | L6: 2
A7: P006 | B7: Electronics | C7: Smartwatch | D7: Lifestyle Product | E7: Personal Tech | F7: 9500 | G7: 30 | H7: =Table10[[#This Row],[Unit_Price (₹)]]*(1-Table10[[#This Row],[Profit_Margin (%)]]/100) -> 6650 | I7: Medium | J7: High | K7: 1 | L7: 3
A8: P007 | B8: Electronics | C8: External Hard Drive | D8: Storage Essential | E8: Tech Essentials | F8: 6900 | G8: 17 | H8: =Table10[[#This Row],[Unit_Price (₹)]]*(1-Table10[[#This Row],[Profit_Margin (%)]]/100) -> 5727 | I8: Low | J8: Medium | K8: 1 | L8: 2
A9: P008 | B9: Electronics | C9: Earbuds | D9: Profit Stabilizer | E9: Tech Essentials | F9: 3590 | G9: 35 | H9: =Table10[[#This Row],[Unit_Price (₹)]]*(1-Table10[[#This Row],[Profit_Margin (%)]]/100) -> 2333.5 | I9: High | J9: High | K9: 1 | L9: 4
A10: P009 | B10: Electronics | C10: Keyboard | D10: Workspace Essential | E10: Workspace Setup | F10: 1650 | G10: 40 | H10: =Table10[[#This Row],[Unit_Price (₹)]]*(1-Table10[[#This Row],[Profit_Margin (%)]]/100) -> 990 | I10: High | J10: Medium | K10: 1 | L10: 5
A11: P010 | B11: Electronics | C11: Mouse | D11: Workspace Essential | E11: Workspace Setup | F11: 1100 | G11: 35 | H11: =Table10[[#This Row],[Unit_Price (₹)]]*(1-Table10[[#This Row],[Profit_Margin (%)]]/100) -> 715 | I11: High | J11: Medium | K11: 1 | L11: 5
A12: P011 | B12: Furniture | C12: Office Chair | D12: Workspace Traffic Builder | E12: Workspace Setup | F12: 8999 | G12: 28 | H12: =Table10[[#This Row],[Unit_Price (₹)]]*(1-Table10[[#This Row],[Profit_Margin (%)]]/100) -> 6479.28 | I12: Medium-High | J12: Medium | K12: 1 | L12: 4
A13: P012 | B13: Furniture | C13: Study Desk | D13: Workspace Traffic Builder | E13: Workspace Setup | F13: 11999 | G13: 25 | H13: =Table10[[#This Row],[Unit_Price (₹)]]*(1-Table10[[#This Row],[Profit_Margin (%)]]/100) -> 8999.25 | I13: Medium | J13: Medium | K13: 1 | L13: 2
... A22: P021 | B22: Office Supplies | C22: Calculator | D22: Academic Essential | E22: Study Essentials | F22: 650 | G22: 28 | H22: =Table10[[#This Row],[Unit_Price (₹)]]*(1-Table10[[#This Row],[Profit_Margin (%)]]/100) -> 468 | I22: Medium | J22: High | K22: 1 | L22: 3
